Workbook

Sheet Запчасти
A1: Артикул | B1: Наименование | C1: Производитель | D1: Подходит к авто | E1: Категория | F1: Дата поступления | G1: Закупочная цена | H1: Цена продажи | I1: Поступило | J1: Продано | K1: Остаток | L1: Всего на сумму | M1: Выручка | N1: Себестоимость проданного | O1: Прибыль | P1: Комментарий | Q1: Артикул (текст) | R1: autogur73.ru, RUB | S1: chipdip.kz, KZT | T1: uaz.store, RUB | U1: metalpart.ru, RUB | V1: detaliuaz.ru, RUB | W1: vta-gaz.ru, RUB | X1: spectuninguaz.ru, RUB | Y1: 4uaz.ru, RUB | Z1: Kaspi, KZT | AA1: Ozon, KZT | AB1: Найдено цен | AC1: Средняя цена рынка, ₸ | AD1: Своя наценка, % | AE1: Наценка итого, % | AF1: Новая цена, ₸ | AG1: Текущая цена к рынку | AH1: Ссылки / заметки по ценам
A2: 4693501070 | B2: Задний тормозной барабан | C2: Уаз | D2: УАЗ Буханка | E2: Тормоза | H2: 20000 | I2: 13 | K2: =I2-J2 -> 13 | L2: =K2*H2 -> 260000 | M2: =IF(A2="","",H2*J2) -> 0 | N2: =IF(A2="","",G2*J2) -> 0 | O2: =IF(A2="","",M2-N2) -> 0 | Q2: 4693501070 | AB2: =SUMPRODUCT(--(R2:AA2>0),'Настройки цен'!$B$12:$K$12) -> 0 | AC2: =IF(AB2=0,"",SUMPRODUCT(R2:AA2,'Настройки цен'!$B$11:$K$11,'Настройки цен'!$B$12:$K$12)/AB2) | AE2: =IF(AD2<>"",AD2,IFERROR(IF(INDEX('Настройки цен'!$B$17:$B$24,MATCH(E2,'Настройки цен'!$A$17:$A$24,0))="",'Настройки цен'!$B$5,INDEX('Настройки цен'!$B$17:$B$24,MATCH(E2,'Настройки цен'!$A$17:$A$24,0))),'Настройки цен'!$B$5)) -> 0 | AF2: =IF(AC2="","",ROUND(AC2*(1+AE2)/'Настройки цен'!$B$6,0)*'Настройки цен'!$B$6) | AG2: =IF(OR(AC2="",H2=""),"",H2/AC2-1) | AH2: Не в списке сайтов, для справки: АДС ~3 200 ₽, оригинал УАЗ ~5 000–6 000 ₽ (sparox.ru, uazist.ru). Цена сильно зависит от производителя.
A3: 37413502013 | B3: Тормозной щит | C3: УАЗ | D3: УАЗ Буханка | E3: Тормоза | H3: 15000 | I3: 4 | K3: =I3-J3 -> 4 | L3: =K3*H3 -> 60000 | M3: =IF(A3="","",H3*J3) -> 0 | N3: =IF(A3="","",G3*J3) -> 0 | O3: =IF(A3="","",M3-N3) -> 0 | Q3: 37413502013 | AB3: =SUMPRODUCT(--(R3:AA3>0),'Настройки цен'!$B$12:$K$12) -> 0 | AC3: =IF(AB3=0,"",SUMPRODUCT(R3:AA3,'Настройки цен'!$B$11:$K$11,'Настройки цен'!$B$12:$K$12)/AB3) | AE3: =IF(AD3<>"",AD3,IFERROR(IF(INDEX('Настройки цен'!$B$17:$B$24,MATCH(E3,'Настройки цен'!$A$17:$A$24,0))="",'Настройки цен'!$B$5,INDEX('Настройки цен'!$B$17:$B$24,MATCH(E3,'Настройки цен'!$A$17:$A$24,0))),'Настройки цен'!$B$5)) -> 0 | AF3: =IF(AC3="","",ROUND(AC3*(1+AE3)/'Настройки цен'!$B$6,0)*'Настройки цен'!$B$6) | AG3: =IF(OR(AC3="",H3=""),"",H3/AC3-1)
A4: 316000350108400 | B4: Щиток тормозного диска | C4: УАЗ | D4: УАЗ Буханка | E4: Тормоза | H4: 4000 | I4: 18 | K4: =I4-J4 -> 18 | L4: =K4*H4 -> 72000 | M4: =IF(A4="","",H4*J4) -> 0 | N4: =IF(A4="","",G4*J4) -> 0 | O4: =IF(A4="","",M4-N4) -> 0 | Q4: 316000350108400 | AB4: =SUMPRODUCT(--(R4:AA4>0),'Настройки цен'!$B$12:$K$12) -> 0 | AC4: =IF(AB4=0,"",SUMPRODUCT(R4:AA4,'Настройки цен'!$B$11:$K$11,'Настройки цен'!$B$12:$K$12)/AB4) | AE4: =IF(AD4<>"",AD4,IFERROR(IF(INDEX('Настройки цен'!$B$17:$B$24,MATCH(E4,'Настройки цен'!$A$17:$A$24,0))="",'Настройки цен'!$B$5,INDEX('Настройки цен'!$B$17:$B$24,MATCH(E4,'Настройки цен'!$A$17:$A$24,0))),'Настройки цен'!$B$5)) -> 0 | AF4: =IF(AC4="","",ROUND(AC4*(1+AE4)/'Настройки цен'!$B$6,0)*'Настройки цен'!$B$6) | AG4: =IF(OR(AC4="",H4=""),"",H4/AC4-1)
A5: 31603501014 | B5: Тормозной суппорт УАЗ | D5: УАЗ Буханка | E5: Тормоза | H5: 45000 | I5: 11 | K5: =I5-J5 -> 11 | L5: =K5*H5 -> 495000 | M5: =IF(A5="","",H5*J5) -> 0 | N5: =IF(A5="","",G5*J5) -> 0 | O5: =IF(A5="","",M5-N5) -> 0 | Q5: 31603501014 | V5: 8429 | AB5: =SUMPRODUCT(--(R5:AA5>0),'Настройки цен'!$B$12:$K$12) -> 1 | AC5: =IF(AB5=0,"",SUMPRODUCT(R5:AA5,'Настройки цен'!$B$11:$K$11,'Настройки цен'!$B$12:$K$12)/AB5) -> 44673.7 | AE5: =IF(AD5<>"",AD5,IFERROR(IF(INDEX('Настройки цен'!$B$17:$B$24,MATCH(E5,'Настройки цен'!$A$17:$A$24,0))="",'Настройки цен'!$B$5,INDEX('Настройки цен'!$B$17:$B$24,MATCH(E5,'Настройки цен'!$A$17:$A$24,0))),'Настройки цен'!$B$5)) -> 0 | AF5: =IF(AC5="","",ROUND(AC5*(1+AE5)/'Настройки цен'!$B$6,0)*'Настройки цен'!$B$6) -> 44700 | AG5: =IF(OR(AC5="",H5=""),"",H5/AC5-1) -> 0.0073040738 | AH5: detaliuaz.ru: суппорт УАЗ-3160 левый 8 429 ₽ (правый 9 357 ₽). ВНИМАНИЕ: по каталогам 3163-3501014 — это скоба суппорта, а не суппорт. Сверить деталь.
A6: 3160350107602 | B6: Тормозной диск | D6: УАЗ Буханка | E6: Тормоза | H6: 15000 | I6: 5 | K6: =I6-J6 -> 5 | L6: =K6*H6 -> 75000 | M6: =IF(A6="","",H6*J6) -> 0 | N6: =IF(A6="","",G6*J6) -> 0 | O6: =IF(A6="","",M6-N6) -> 0 | Q6: 3160350107602 | AB6: =SUMPRODUCT(--(R6:AA6>0),'Настройки цен'!$B$12:$K$12) -> 0 | AC6: =IF(AB6=0,"",SUMPRODUCT(R6:AA6,'Настройки цен'!$B$11:$K$11,'Настройки цен'!$B$12:$K$12)/AB6) | AE6: =IF(AD6<>"",AD6,IFERROR(IF(INDEX('Настройки цен'!$B$17:$B$24,MATCH(E6,'Настройки цен'!$A$17:$A$24,0))="",'Настройки цен'!$B$5,INDEX('Настройки цен'!$B$17:$B$24,MATCH(E6,'Настройки цен'!$A$17:$A$24,0))),'Настройки цен'!$B$5)) -> 0 | AF6: =IF(AC6="","",ROUND(AC6*(1+AE6)/'Настройки цен'!$B$6,0)*'Настройки цен'!$B$6) | AG6: =IF(OR(AC6="",H6=""),"",H6/AC6-1)
A7: 220600350209110 | B7: Задние тормозные колодки | D7: УАЗ Буханка | E7: Тормоза | H7: 5000 | I7: 49 | K7: =I7-J7 -> 49 | L7: =K7*H7 -> 245000 | M7: =IF(A7="","",H7*J7) -> 0 | N7: =IF(A7="","",G7*J7) -> 0 | O7: =IF(A7="","",M7-N7) -> 0 | Q7: 220600350209110 | AB7: =SUMPRODUCT(--(R7:AA7>0),'Настройки цен'!$B$12:$K$12) -> 0 | AC7: =IF(AB7=0,"",SUMPRODUCT(R7:AA7,'Настройки цен'!$B$11:$K$11,'Настройки цен'!$B$12:$K$12)/AB7) | AE7: =IF(AD7<>"",AD7,IFERROR(IF(INDEX('Настройки цен'!$B$17:$B$24,MATCH(E7,'Настройки цен'!$A$17:$A$24,0))="",'Настройки цен'!$B$5,INDEX('Настройки цен'!$B$17:$B$24,MATCH(E7,'Настройки цен'!$A$17:$A$24,0))),'Настройки цен'!$B$5)) -> 0 | AF7: =IF(AC7="","",ROUND(AC7*(1+AE7)/'Настройки цен'!$B$6,0)*'Настройки цен'!$B$6) | AG7: =IF(OR(AC7="",H7=""),"",H7/AC7-1)
A8: 316300350108805 | B8: Дисковые колодки тормозные | D8: УАЗ Буханка | E8: Тормоза | H8: 8000 | I8: 9 | K8: =I8-J8 -> 9 | L8: =K8*H8 -> 72000 | M8: =IF(A8="","",H8*J8) -> 0 | N8: =IF(A8="","",G8*J8) -> 0 | O8: =IF(A8="","",M8-N8) -> 0 | Q8: 316300350108805 | AB8: =SUMPRODUCT(--(R8:AA8>0),'Настройки цен'!$B$12:$K$12) -> 0 | AC8: =IF(AB8=0,"",SUMPRODUCT(R8:AA8,'Настройки цен'!$B$11:$K$11,'Настройки цен'!$B$12:$K$12)/AB8) | AE8: =IF(AD8<>"",AD8,IFERROR(IF(INDEX('Настройки цен'!$B$17:$B$24,MATCH(E8,'Настройки цен'!$A$17:$A$24,0))="",'Настройки цен'!$B$5,INDEX('Настройки цен'!$B$17:$B$24,MATCH(E8,'Настройки цен'!$A$17:$A$24,0))),'Настройки цен'!$B$5)) -> 0 | AF8: =IF(AC8="","",ROUND(AC8*(1+AE8)/'Настройки цен'!$B$6,0)*'Настройки цен'!$B$6) | AG8: =IF(OR(AC8="",H8=""),"",H8/AC8-1)
A9: 31632304019 | B9: Ремкомплект шкворня моста спайсер | D9: УАЗ Буханка | E9: Подвеска | H9: 15000 | I9: 5 | K9: =I9-J9 -> 5 | L9: =K9*H9 -> 75000 | M9: =IF(A9="","",H9*J9) -> 0 | N9: =IF(A9="","",G9*J9) -> 0 | O9: =IF(A9="","",M9-N9) -> 0 | Q9: 31632304019 | AB9: =SUMPRODUCT(--(R9:AA9>0),'Настройки цен'!$B$12:$K$12) -> 0 | AC9: =IF(AB9=0,"",SUMPRODUCT(R9:AA9,'Настройки цен'!$B$11:$K$11,'Настройки цен'!$B$12:$K$12)/AB9) | AE9: =IF(AD9<>"",AD9,IFERROR(IF(INDEX('Настройки цен'!$B$17:$B$24,MATCH(E9,'Настройки цен'!$A$17:$A$24,0))="",'Настройки цен'!$B$5,INDEX('Настройки цен'!$B$17:$B$24,MATCH(E9,'Настройки цен'!$A$17:$A$24,0))),'Настройки цен'!$B$5)) -> 0 | AF9: =IF(AC9="","",ROUND(AC9*(1+AE9)/'Настройки цен'!$B$6,0)*'Настройки цен'!$B$6) | AG9: =IF(OR(AC9="",H9=""),"",H9/AC9-1)
A10: 315120230440001 | B10: Хабы оригинал (комплект) | D10: УАЗ | E10: Подвеска | H10: 50000 | I10: 1 | K10: =I10-J10 -> 1 | L10: =K10*H10 -> 50000 | M10: =IF(A10="","",H10*J10) -> 0 | N10: =IF(A10="","",G10*J10) -> 0 | O10: =IF(A10="","",M10-N10) -> 0 | Q10: 315120230440001 | AB10: =SUMPRODUCT(--(R10:AA10>0),'Настройки цен'!$B$12:$K$12) -> 0 | AC10: =IF(AB10=0,"",SUMPRODUCT(R10:AA10,'Настройки цен'!$B$11:$K$11,'Настройки цен'!$B$12:$K$12)/AB10) | AE10: =IF(AD10<>"",AD10,IFERROR(IF(INDEX('Настройки цен'!$B$17:$B$24,MATCH(E10,'Настройки цен'!$A$17:$A$24,0))="",'Настройки цен'!$B$5,INDEX('Настройки цен'!$B$17:$B$24,MATCH(E10,'Настройки цен'!$A$17:$A$24,0))),'Настройки цен'!$B$5)) -> 0 | AF10: =IF(AC10="","",ROUND(AC10*(1+AE10)/'Настройки цен'!$B$6,0)*'Настройки цен'!$B$6) | AG10: =IF(OR(AC10="",H10=""),"",H10/AC10-1)
B11: Ремкомплект поворотного кулака Хантер | D11: УАЗ | E11: Подвеска | H11: 5000 | I11: 16 | K11: =I11-J11 -> 16 | L11: =K11*H11 -> 80000 | M11: =IF(A11="","",H11*J11) | N11: =IF(A11="","",G11*J11) | O11: =IF(A11="","",M11-N11) | AB11: =SUMPRODUCT(--(R11:AA11>0),'Настройки цен'!$B$12:$K$12) -> 0 | AC11: =IF(AB11=0,"",SUMPRODUCT(R11:AA11,'Настройки цен'!$B$11:$K$11,'Настройки цен'!$B$12:$K$12)/AB11) | AE11: =IF(AD11<>"",AD11,IFERROR(IF(INDEX('Настройки цен'!$B$17:$B$24,MATCH(E11,'Настройки цен'!$A$17:$A$24,0))="",'Настройки цен'!$B$5,INDEX('Настройки цен'!$B$17:$B$24,MATCH(E11,'Настройки цен'!$A$17:$A$24,0))),'Настройки цен'!$B$5)) -> 0 | AF11: =IF(AC11="","",ROUND(AC11*(1+AE11)/'Настройки цен'!$B$6,0)*'Настройки цен'!$B$6) | AG11: =IF(OR(AC11="",H11=""),"",H11/AC11-1)
B12: Чашки листа рессоры + заклепки | D12: Уаз | E12: Подвеска | H12: 10000 | I12: 50 | K12: =I12-J12 -> 50 | L12: =K12*H12 -> 500000 | M12: =IF(A12="","",H12*J12) | N12: =IF(A12="","",G12*J12) | O12: =IF(A12="","",M12-N12) | AB12: =SUMPRODUCT(--(R12:AA12>0),'Настройки цен'!$B$12:$K$12) -> 0 | AC12: =IF(AB12=0,"",SUMPRODUCT(R12:AA12,'Настройки цен'!$B$11:$K$11,'Настройки цен'!$B$12:$K$12)/AB12) | AE12: =IF(AD12<>"",AD12,IFERROR(IF(INDEX('Настройки цен'!$B$17:$B$24,MATCH(E12,'Настройки цен'!$A$17:$A$24,0))="",'Настройки цен'!$B$5,INDEX('Настройки цен'!$B$17:$B$24,MATCH(E12,'Настройки цен'!$A$17:$A$24,0))),'Настройки цен'!$B$5)) -> 0 | AF12: =IF(AC12="","",ROUND(AC12*(1+AE12)/'Настройки цен'!$B$6,0)*'Настройки цен'!$B$6) | AG12: =IF(OR(AC12="",H12=""),"",H12/AC12-1)
B13: Ремкомплект шкворня моста Хантер | D13: Уаз | E13: Подвеска | H13: 15000 | I13: 2 | K13: =I13-J13 -> 2 | L13: =K13*H13 -> 30000 | M13: =IF(A13="","",H13*J13) | N13: =IF(A13="","",G13*J13) | O13: =IF(A13="","",M13-N13) | AB13: =SUMPRODUCT(--(R13:AA13>0),'Настройки цен'!$B$12:$K$12) -> 0 | AC13: =IF(AB13=0,"",SUMPRODUCT(R13:AA13,'Настройки цен'!$B$11:$K$11,'Настройки цен'!$B$12:$K$12)/AB13) | AE13: =IF(AD13<>"",AD13,IFERROR(IF(INDEX('Настройки цен'!$B$17:$B$24,MATCH(E13,'Настройки цен'!$A$17:$A$24,0))="",'Настройки цен'!$B$5,INDEX('Настройки цен'!$B$17:$B$24,MATCH(E13,'Настройки цен'!$A$17:$A$24,0))),'Настройки цен'!$B$5)) -> 0 | AF13: =IF(AC13="","",ROUND(AC13*(1+AE13)/'Настройки цен'!$B$6,0)*'Настройки цен'!$B$6) | AG13: =IF(OR(AC13="",H13=""),"",H13/AC13-1)
A14: 42x68x16.4 | B14: Сальник хвостовика раздаточной коробки | D14: УАЗ | E14: Подвеска | H14: 1500 | I14: 13 | K14: =I14-J14 -> 13 | L14: =K14*H14 -> 19500 | M14: =IF(A14="","",H14*J14) -> 0 | N14: =IF(A14="","",G14*J14) -> 0 | O14: =IF(A14="","",M14-N14) -> 0 | Q14: 42x68x16.4 | AB14: =SUMPRODUCT(--(R14:AA14>0),'Настройки цен'!$B$12:$K$12) -> 0 | AC14: =IF(AB14=0,"",SUMPRODUCT(R14:AA14,'Настройки цен'!$B$11:$K$11,'Настройки цен'!$B$12:$K$12)/AB14) | AE14: =IF(AD14<>"",AD14,IFERROR(IF(INDEX('Настройки цен'!$B$17:$B$24,MATCH(E14,'Настройки цен'!$A$17:$A$24,0))="",'Настройки цен'!$B$5,INDEX('Настройки цен'!$B$17:$B$24,MATCH(E14,'Настройки цен'!$A$17:$A$24,0))),'Настройки цен'!$B$5)) -> 0 | AF14: =IF(AC14="","",ROUND(AC14*(1+AE14)/'Настройки цен'!$B$6,0)*'Настройки цен'!$B$6) | AG14: =IF(OR(AC14="",H14=""),"",H14/AC14-1)
A15: 38x56x10 | B15: Сальник в кпп | D15: ГАЗ | E15: Подвеска | H15: 1000 | I15: 30 | K15: =I15-J15 -> 30 | L15: =K15*H15 -> 30000 | M15: =IF(A15="","",H15*J15) -> 0 | N15: =IF(A15="","",G15*J15) -> 0 | O15: =IF(A15="","",M15-N15) -> 0 | Q15: 38x56x10 | AB15: =SUMPRODUCT(--(R15:AA15>0),'Настройки цен'!$B$12:$K$12) -> 0 | AC15: =IF(AB15=0,"",SUMPRODUCT(R15:AA15,'Настройки цен'!$B$11:$K$11,'Настройки цен'!$B$12:$K$12)/AB15) | AE15: =IF(AD15<>"",AD15,IFERROR(IF(INDEX('Настройки цен'!$B$17:$B$24,MATCH(E15,'Настройки цен'!$A$17:$A$24,0))="",'Настройки цен'!$B$5,INDEX('Настройки цен'!$B$17:$B$24,MATCH(E15,'Настройки цен'!$A$17:$A$24,0))),'Настройки цен'!$B$5)) -> 0 | AF15: =IF(AC15="","",ROUND(AC15*(1+AE15)/'Настройки цен'!$B$6,0)*'Настройки цен'!$B$6) | AG15: =IF(OR(AC15="",H15=""),"",H15/AC15-1)
A16: 40x56x7.5 | B16: Сальник коленвала | D16: ВАЗ | E16: Двигатель | H16: 2000 | I16: 10 | K16: =I16-J16 -> 10 | L16: =K16*H16 -> 20000 | M16: =IF(A16="","",H16*J16) -> 0 | N16: =IF(A16="","",G16*J16) -> 0 | O16: =IF(A16="","",M16-N16) -> 0 | Q16: 40x56x7.5 | AB16: =SUMPRODUCT(--(R16:AA16>0),'Настройки цен'!$B$12:$K$12) -> 0 | AC16: =IF(AB16=0,"",SUMPRODUCT(R16:AA16,'Настройки цен'!$B$11:$K$11,'Настройки цен'!$B$12:$K$12)/AB16) | AE16: =IF(AD16<>"",AD16,IFERROR(IF(INDEX('Настройки цен'!$B$17:$B$24,MATCH(E16,'Настройки цен'!$A$17:$A$24,0))="",'Настройки цен'!$B$5,INDEX('Настройки цен'!$B$17:$B$24,MATCH(E16,'Настройки цен'!$A$17:$A$24,0))),'Настройки цен'!$B$5)) -> 0 | AF16: =IF(AC16="","",ROUND(AC16*(1+AE16)/'Настройки цен'!$B$6,0)*'Настройки цен'!$B$6) | AG16: =IF(OR(AC16="",H16=""),"",H16/AC16-1)
A17: 80x100x10 | B17: Сальник коленвала | D17: ВАЗ | E17: Двигатель | H17: 4000 | I17: 40 | K17: =I17-J17 -> 40 | L17: =K17*H17 -> 160000 | M17: =IF(A17="","",H17*J17) -> 0 | N17: =IF(A17="","",G17*J17) -> 0 | O17: =IF(A17="","",M17-N17) -> 0 | Q17: 80x100x10 | AB17: =SUMPRODUCT(--(R17:AA17>0),'Настройки цен'!$B$12:$K$12) -> 0 | AC17: =IF(AB17=0,"",SUMPRODUCT(R17:AA17,'Настройки цен'!$B$11:$K$11,'Настройки цен'!$B$12:$K$12)/AB17) | AE17: =IF(AD17<>"",AD17,IFERROR(IF(INDEX('Настройки цен'!$B$17:$B$24,MATCH(E17,'Настройки цен'!$A$17:$A$24,0))="",'Настройки цен'!$B$5,INDEX('Настройки цен'!$B$17:$B$24,MATCH(E17,'Настройки цен'!$A$17:$A$24,0))),'Настройки цен'!$B$5)) -> 0 | AF17: =IF(AC17="","",ROUND(AC17*(1+AE17)/'Настройки цен'!$B$6,0)*'Настройки цен'!$B$6) | AG17: =IF(OR(AC17="",H17=""),"",H17/AC17-1)
A18: 21212202025 | B18: Крестовина нива | D18: ВАЗ | E18: Подвеска | H18: 4000 | I18: 1 | K18: =I18-J18 -> 1 | L18: =K18*H18 -> 4000 | M18: =IF(A18="","",H18*J18) -> 0 | N18: =IF(A18="","",G18*J18) -> 0 | O18: =IF(A18="","",M18-N18) -> 0 | Q18: 21212202025 | AB18: =SUMPRODUCT(--(R18:AA18>0),'Настройки цен'!$B$12:$K$12) -> 0 | AC18: =IF(AB18=0,"",SUMPRODUCT(R18:AA18,'Настройки цен'!$B$11:$K$11,'Настройки цен'!$B$12:$K$12)/AB18) | AE18: =IF(AD18<>"",AD18,IFERROR(IF(INDEX('Настройки цен'!$B$17:$B$24,MATCH(E18,'Настройки цен'!$A$17:$A$24,0))="",'Настройки цен'!$B$5,INDEX('Настройки цен'!$B$17:$B$24,MATCH(E18,'Настройки цен'!$A$17:$A$24,0))),'Настройки цен'!$B$5)) -> 0 | AF18: =IF(AC18="","",ROUND(AC18*(1+AE18)/'Настройки цен'!$B$6,0)*'Настройки цен'!$B$6) | AG18: =IF(OR(AC18="",H18=""),"",H18/AC18-1)
A19: 21052202025 | B19: Крестовина Жигули | D19: ВАЗ | E19: Подвеска | H19: 3000 | I19: 16 | K19: =I19-J19 -> 16 | L19: =K19*H19 -> 48000 | M19: =IF(A19="","",H19*J19) -> 0 | N19: =IF(A19="","",G19*J19) -> 0 | O19: =IF(A19="","",M19-N19) -> 0 | Q19: 21052202025 | AB19: =SUMPRODUCT(--(R19:AA19>0),'Настройки цен'!$B$12:$K$12) -> 0 | AC19: =IF(AB19=0,"",SUMPRODUCT(R19:AA19,'Настройки цен'!$B$11:$K$11,'Настройки цен'!$B$12:$K$12)/AB19) | AE19: =IF(AD19<>"",AD19,IFERROR(IF(INDEX('Настройки цен'!$B$17:$B$24,MATCH(E19,'Настройки цен'!$A$17:$A$24,0))="",'Настройки цен'!$B$5,INDEX('Настройки цен'!$B$17:$B$24,MATCH(E19,'Настройки цен'!$A$17:$A$24,0))),'Настройки цен'!$B$5)) -> 0 | AF19: =IF(AC19="","",ROUND(AC19*(1+AE19)/'Настройки цен'!$B$6,0)*'Настройки цен'!$B$6) | AG19: =IF(OR(AC19="",H19=""),"",H19/AC19-1)
A20: 469003501041496 | B20: Тормозной цилиндр передний левый | D20: УАЗ | E20: Тормоза | H20: 5000 | I20: 13 | K20: =I20-J20 -> 13 | L20: =K20*H20 -> 65000 | M20: =IF(A20="","",H20*J20) -> 0 | N20: =IF(A20="","",G20*J20) -> 0 | O20: =IF(A20="","",M20-N20) -> 0 | Q20: 469003501041496 | AB20: =SUMPRODUCT(--(R20:AA20>0),'Настройки цен'!$B$12:$K$12) -> 0 | AC20: =IF(AB20=0,"",SUMPRODUCT(R20:AA20,'Настройки цен'!$B$11:$K$11,'Настройки цен'!$B$12:$K$12)/AB20) | AE20: =IF(AD20<>"",AD20,IFERROR(IF(INDEX('Настройки цен'!$B$17:$B$24,MATCH(E20,'Настройки цен'!$A$17:$A$24,0))="",'Настройки цен'!$B$5,INDEX('Настройки цен'!$B$17:$B$24,MATCH(E20,'Настройки цен'!$A$17:$A$24,0))),'Настройки цен'!$B$5)) -> 0 | AF20: =IF(AC20="","",ROUND(AC20*(1+AE20)/'Настройки цен'!$B$6,0)*'Настройки цен'!$B$6) | AG20: =IF(OR(AC20="",H20=""),"",H20/AC20-1)
A21: 469003501040496 | B21: Тормозной цилиндр передний правый | D21: Уаз | E21: Тормоза | H21: 5000 | I21: 4 | K21: =I21-J21 -> 4 | L21: =K21*H21 -> 20000 | M21: =IF(A21="","",H21*J21) -> 0 | N21: =IF(A21="","",G21*J21) -> 0 | O21: =IF(A21="","",M21-N21) -> 0 | Q21: 469003501040496 | AB21: =SUMPRODUCT(--(R21:AA21>0),'Настройки цен'!$B$12:$K$12) -> 0 | AC21: =IF(AB21=0,"",SUMPRODUCT(R21:AA21,'Настройки цен'!$B$11:$K$11,'Настройки цен'!$B$12:$K$12)/AB21) | AE21: =IF(AD21<>"",AD21,IFERROR(IF(INDEX('Настройки цен'!$B$17:$B$24,MATCH(E21,'Настройки цен'!$A$17:$A$24,0))="",'Настройки цен'!$B$5,INDEX('Настройки цен'!$B$17:$B$24,MATCH(E21,'Настройки цен'!$A$17:$A$24,0))),'Настройки цен'!$B$5)) -> 0 | AF21: =IF(AC21="","",ROUND(AC21*(1+AE21)/'Настройки цен'!$B$6,0)*'Настройки цен'!$B$6) | AG21: =IF(OR(AC21="",H21=""),"",H21/AC21-1)
B22: Шаровая опора поворотного кулака | D22: УАЗ | E22: Подвеска | H22: 50000 | I22: 5 | K22: =I22-J22 -> 5 | L22: =K22*H22 -> 250000 | M22: =IF(A22="","",H22*J22) | N22: =IF(A22="","",G22*J22) | O22: =IF(A22="","",M22-N22) | AB22: =SUMPRODUCT(--(R22:AA22>0),'Настройки цен'!$B$12:$K$12) -> 0 | AC22: =IF(AB22=0,"",SUMPRODUCT(R22:AA22,'Настройки цен'!$B$11:$K$11,'Настройки цен'!$B$12:$K$12)/AB22) | AE22: =IF(AD22<>"",AD22,IFERROR(IF(INDEX('Настройки цен'!$B$17:$B$24,MATCH(E22,'Настройки цен'!$A$17:$A$24,0))="",'Настройки цен'!$B$5,INDEX('Настройки цен'!$B$17:$B$24,MATCH(E22,'Настройки цен'!$A$17:$A$24,0))),'Настройки цен'!$B$5)) -> 0 | AF22: =IF(AC22="","",ROUND(AC22*(1+AE22)/'Настройки цен'!$B$6,0)*'Настройки цен'!$B$6) | AG22: =IF(OR(AC22="",H22=""),"",H22/AC22-1)
A23: 4171002060 | B23: Передняя крышка блока цилиндров | D23: УАЗ/ГАЗ | E23: Двигатель | H23: 20000 | I23: 3 | K23: =I23-J23 -> 3 | L23: =K23*H23 -> 60000 | M23: =IF(A23="","",H23*J23) -> 0 | N23: =IF(A23="","",G23*J23) -> 0 | O23: =IF(A23="","",M23-N23) -> 0 | Q23: 4171002060 | AB23: =SUMPRODUCT(--(R23:AA23>0),'Настройки цен'!$B$12:$K$12) -> 0 | AC23: =IF(AB23=0,"",SUMPRODUCT(R23:AA23,'Настройки цен'!$B$11:$K$11,'Настройки цен'!$B$12:$K$12)/AB23) | AE23: =IF(AD23<>"",AD23,IFERROR(IF(INDEX('Настройки цен'!$B$17:$B$24,MATCH(E23,'Настройки цен'!$A$17:$A$24,0))="",'Настройки цен'!$B$5,INDEX('Настройки цен'!$B$17:$B$24,MATCH(E23,'Настройки цен'!$A$17:$A$24,0))),'Настройки цен'!$B$5)) -> 0 | AF23: =IF(AC23="","",ROUND(AC23*(1+AE23)/'Настройки цен'!$B$6,0)*'Настройки цен'!$B$6) | AG23: =IF(OR(AC23="",H23=""),"",H23/AC23-1)
A24: 45x85x24.75 | B24: Подшипник ступицы | D24: УАЗ | E24: Подвеска | H24: 5000 | I24: 17 | K24: =I24-J24 -> 17 | L24: =K24*H24 -> 85000 | M24: =IF(A24="","",H24*J24) -> 0 | N24: =IF(A24="","",G24*J24) -> 0 | O24: =IF(A24="","",M24-N24) -> 0 | Q24: 45x85x24.75 | AB24: =SUMPRODUCT(--(R24:AA24>0),'Настройки цен'!$B$12:$K$12) -> 0 | AC24: =IF(AB24=0,"",SUMPRODUCT(R24:AA24,'Настройки цен'!$B$11:$K$11,'Настройки цен'!$B$12:$K$12)/AB24) | AE24: =IF(AD24<>"",AD24,IFERROR(IF(INDEX('Настройки цен'!$B$17:$B$24,MATCH(E24,'Настройки цен'!$A$17:$A$24,0))="",'Настройки цен'!$B$5,INDEX('Настройки цен'!$B$17:$B$24,MATCH(E24,'Настройки цен'!$A$17:$A$24,0))),'Настройки цен'!$B$5)) -> 0 | AF24: =IF(AC24="","",ROUND(AC24*(1+AE24)/'Настройки цен'!$B$6,0)*'Настройки цен'!$B$6) | AG24: =IF(OR(AC24="",H24=""),"",H24/AC24-1)
A25: 50x90x24.75 | B25: Подшипник дифференциала | D25: Уаз | E25: Подвеска | H25: 6000 | I25: 2 | K25: =I25-J25 -> 2 | L25: =K25*H25 -> 12000 | M25: =IF(A25="","",H25*J25) -> 0 | N25: =IF(A25="","",G25*J25) -> 0 | O25: =IF(A25="","",M25-N25) -> 0 | Q25: 50x90x24.75 | AB25: =SUMPRODUCT(--(R25:AA25>0),'Настройки цен'!$B$12:$K$12) -> 0 | AC25: =IF(AB25=0,"",SUMPRODUCT(R25:AA25,'Настройки цен'!$B$11:$K$11,'Настройки цен'!$B$12:$K$12)/AB25) | AE25: =IF(AD25<>"",AD25,IFERROR(IF(INDEX('Настройки цен'!$B$17:$B$24,MATCH(E25,'Настройки цен'!$A$17:$A$24,0))="",'Настройки цен'!$B$5,INDEX('Настройки цен'!$B$17:$B$24,MATCH(E25,'Настройки цен'!$A$17:$A$24,0))),'Настройки цен'!$B$5)) -> 0 | AF25: =IF(AC25="","",ROUND(AC25*(1+AE25)/'Настройки цен'!$B$6,0)*'Настройки цен'!$B$6) | AG25: =IF(OR(AC25="",H25=""),"",H25/AC25-1)
B26: Хабы Noname (комплект) | D26: УАЗ | E26: Подвеска | H26: 40000 | I26: 4 | K26: =I26-J26 -> 4 | L26: =K26*H26 -> 160000 | M26: =IF(A26="","",H26*J26) | N26: =IF(A26="","",G26*J26) | O26: =IF(A26="","",M26-N26) | AB26: =SUMPRODUCT(--(R26:AA26>0),'Настройки цен'!$B$12:$K$12) -> 0 | AC26: =IF(AB26=0,"",SUMPRODUCT(R26:AA26,'Настройки цен'!$B$11:$K$11,'Настройки цен'!$B$12:$K$12)/AB26) | AE26: =IF(AD26<>"",AD26,IFERROR(IF(INDEX('Настройки цен'!$B$17:$B$24,MATCH(E26,'Настройки цен'!$A$17:$A$24,0))="",'Настройки цен'!$B$5,INDEX('Настройки цен'!$B$17:$B$24,MATCH(E26,'Настройки цен'!$A$17:$A$24,0))),'Настройки цен'!$B$5)) -> 0 | AF26: =IF(AC26="","",ROUND(AC26*(1+AE26)/'Настройки цен'!$B$6,0)*'Настройки цен'!$B$6) | AG26: =IF(OR(AC26="",H26=""),"",H26/AC26-1)
A27: 4511701120 | B27: Муфта КПП 3-4 передачи со ступицей | D27: УАЗ | E27: Подвеска | H27: 12000 | I27: 1 | K27: =I27-J27 -> 1 | L27: =K27*H27 -> 12000 | M27: =IF(A27="","",H27*J27) -> 0 | N27: =IF(A27="","",G27*J27) -> 0 | O27: =IF(A27="","",M27-N27) -> 0 | Q27: 4511701120 | AB27: =SUMPRODUCT(--(R27:AA27>0),'Настройки цен'!$B$12:$K$12) -> 0 | AC27: =IF(AB27=0,"",SUMPRODUCT(R27:AA27,'Настройки цен'!$B$11:$K$11,'Настройки цен'!$B$12:$K$12)/AB27) | AE27: =IF(AD27<>"",AD27,IFERROR(IF(INDEX('Настройки цен'!$B$17:$B$24,MATCH(E27,'Настройки цен'!$A$17:$A$24,0))="",'Настройки цен'!$B$5,INDEX('Настройки цен'!$B$17:$B$24,MATCH(E27,'Настройки цен'!$A$17:$A$24,0))),'Настройки цен'!$B$5)) -> 0 | AF27: =IF(AC27="","",ROUND(AC27*(1+AE27)/'Настройки цен'!$B$6,0)*'Настройки цен'!$B$6) | AG27: =IF(OR(AC27="",H27=""),"",H27/AC27-1)
A28: 4691701127 | B28: Шестерня 2й передачи н/о | D28: УАЗ | E28: Подвеска | H28: 15000 | I28: 4 | K28: =I28-J28 -> 4 | L28: =K28*H28 -> 60000 | M28: =IF(A28="","",H28*J28) -> 0 | N28: =IF(A28="","",G28*J28) -> 0 | O28: =IF(A28="","",M28-N28) -> 0 | Q28: 4691701127 | AB28: =SUMPRODUCT(--(R28:AA28>0),'Настройки цен'!$B$12:$K$12) -> 0 | AC28: =IF(AB28=0,"",SUMPRODUCT(R28:AA28,'Настройки цен'!$B$11:$K$11,'Настройки цен'!$B$12:$K$12)/AB28) | AE28: =IF(AD28<>"",AD28,IFERROR(IF(INDEX('Настройки цен'!$B$17:$B$24,MATCH(E28,'Настройки цен'!$A$17:$A$24,0))="",'Настройки цен'!$B$5,INDEX('Настройки цен'!$B$17:$B$24,MATCH(E28,'Настройки цен'!$A$17:$A$24,0))),'Настройки цен'!$B$5)) -> 0 | AF28: =IF(AC28="","",ROUND(AC28*(1+AE28)/'Настройки цен'!$B$6,0)*'Настройки цен'!$B$6) | AG28: =IF(OR(AC28="",H28=""),"",H28/AC28-1)
A29: 45150170111200 | B29: Шестерня 1й передачи | D29: УАЗ | E29: Подвеска | H29: 8000 | I29: 2 | K29: =I29-J29 -> 2 | L29: =K29*H29 -> 16000 | M29: =IF(A29="","",H29*J29) -> 0 | N29: =IF(A29="","",G29*J29) -> 0 | O29: =IF(A29="","",M29-N29) -> 0 | Q29: 45150170111200 | AB29: =SUMPRODUCT(--(R29:AA29>0),'Настройки цен'!$B$12:$K$12) -> 0 | AC29: =IF(AB29=0,"",SUMPRODUCT(R29:AA29,'Настройки цен'!$B$11:$K$11,'Настройки цен'!$B$12:$K$12)/AB29) | AE29: =IF(AD29<>"",AD29,IFERROR(IF(INDEX('Настройки цен'!$B$17:$B$24,MATCH(E29,'Настройки цен'!$A$17:$A$24,0))="",'Настройки цен'!$B$5,INDEX('Настройки цен'!$B$17:$B$24,MATCH(E29,'Настройки цен'!$A$17:$A$24,0))),'Настройки цен'!$B$5)) -> 0 | AF29: =IF(AC29="","",ROUND(AC29*(1+AE29)/'Настройки цен'!$B$6,0)*'Настройки цен'!$B$6) | AG29: =IF(OR(AC29="",H29=""),"",H29/AC29-1)
A30: 61121168 | B30: Шайба стопорная переднего колеса | D30: УАЗ | E30: Подвеска | H30: 500 | I30: 5 | K30: =I30-J30 -> 5 | L30: =K30*H30 -> 2500 | M30: =IF(A30="","",H30*J30) -> 0 | N30: =IF(A30="","",G30*J30) -> 0 | O30: =IF(A30="","",M30-N30) -> 0 | Q30: 61121168 | AB30: =SUMPRODUCT(--(R30:AA30>0),'Настройки цен'!$B$12:$K$12) -> 0 | AC30: =IF(AB30=0,"",SUMPRODUCT(R30:AA30,'Настройки цен'!$B$11:$K$11,'Настройки цен'!$B$12:$K$12)/AB30) | AE30: =IF(AD30<>"",AD30,IFERROR(IF(INDEX('Настройки цен'!$B$17:$B$24,MATCH(E30,'Настройки цен'!$A$17:$A$24,0))="",'Настройки цен'!$B$5,INDEX('Настройки цен'!$B$17:$B$24,MATCH(E30,'Настройки цен'!$A$17:$A$24,0))),'Настройки цен'!$B$5)) -> 0 | AF30: =IF(AC30="","",ROUND(AC30*(1+AE30)/'Настройки цен'!$B$6,0)*'Настройки цен'!$B$6) | AG30: =IF(OR(AC30="",H30=""),"",H30/AC30-1)
A31: 3207 | B31: Подшипник вторичного вала КПП | D31: УАЗ | E31: Подвеска | H31: 5000 | I31: 4 | K31: =I31-J31 -> 4 | L31: =K31*H31 -> 20000 | M31: =IF(A31="","",H31*J31) -> 0 | N31: =IF(A31="","",G31*J31) -> 0 | O31: =IF(A31="","",M31-N31) -> 0 | Q31: 3207 | AB31: =SUMPRODUCT(--(R31:AA31>0),'Настройки цен'!$B$12:$K$12) -> 0 | AC31: =IF(AB31=0,"",SUMPRODUCT(R31:AA31,'Настройки цен'!$B$11:$K$11,'Настройки цен'!$B$12:$K$12)/AB31) | AE31: =IF(AD31<>"",AD31,IFERROR(IF(INDEX('Настройки цен'!$B$17:$B$24,MATCH(E31,'Настройки цен'!$A$17:$A$24,0))="",'Настройки цен'!$B$5,INDEX('Настройки цен'!$B$17:$B$24,MATCH(E31,'Настройки цен'!$A$17:$A$24,0))),'Настройки цен'!$B$5)) -> 0 | AF31: =IF(AC31="","",ROUND(AC31*(1+AE31)/'Настройки цен'!$B$6,0)*'Настройки цен'!$B$6) | AG31: =IF(OR(AC31="",H31=""),"",H31/AC31-1)
A32: 4691701134 | B32: Муфта переключения 1-2й передачи | D32: УАЗ | E32: Подвеска | H32: 25000 | I32: 1 | K32: =I32-J32 -> 1 | L32: =K32*H32 -> 25000 | M32: =IF(A32="","",H32*J32) -> 0 | N32: =IF(A32="","",G32*J32) -> 0 | O32: =IF(A32="","",M32-N32) -> 0 | Q32: 4691701134 | AB32: =SUMPRODUCT(--(R32:AA32>0),'Настройки цен'!$B$12:$K$12) -> 0 | AC32: =IF(AB32=0,"",SUMPRODUCT(R32:AA32,'Настройки цен'!$B$11:$K$11,'Настройки цен'!$B$12:$K$12)/AB32) | AE32: =IF(AD32<>"",AD32,IFERROR(IF(INDEX('Настройки цен'!$B$17:$B$24,MATCH(E32,'Настройки цен'!$A$17:$A$24,0))="",'Настройки цен'!$B$5,INDEX('Настройки цен'!$B$17:$B$24,MATCH(E32,'Настройки цен'!$A$17:$A$24,0))),'Настройки цен'!$B$5)) -> 0 | AF32: =IF(AC32="","",ROUND(AC32*(1+AE32)/'Настройки цен'!$B$6,0)*'Настройки цен'!$B$6) | AG32: =IF(OR(AC32="",H32=""),"",H32/AC32-1)
A33: 4691701116 | B33: Муфта синхронизатора 3-4 й передачи | D33: УАЗ | E33: Подвеска | H33: 25000 | I33: 1 | K33: =I33-J33 -> 1 | L33: =K33*H33 -> 25000 | M33: =IF(A33="","",H33*J33) -> 0 | N33: =IF(A33="","",G33*J33) -> 0 | O33: =IF(A33="","",M33-N33) -> 0 | Q33: 4691701116 | AB33: =SUMPRODUCT(--(R33:AA33>0),'Настройки цен'!$B$12:$K$12) -> 0 | AC33: =IF(AB33=0,"",SUMPRODUCT(R33:AA33,'Настройки цен'!$B$11:$K$11,'Настройки цен'!$B$12:$K$12)/AB33) | AE33: =IF(AD33<>"",AD33,IFERROR(IF(INDEX('Настройки цен'!$B$17:$B$24,MATCH(E33,'Настройки цен'!$A$17:$A$24,0))="",'Настройки цен'!$B$5,INDEX('Настройки цен'!$B$17:$B$24,MATCH(E33,'Настройки цен'!$A$17:$A$24,0))),'Настройки цен'!$B$5)) -> 0 | AF33: =IF(AC33="","",ROUND(AC33*(1+AE33)/'Настройки цен'!$B$6,0)*'Настройки цен'!$B$6) | AG33: =IF(OR(AC33="",H33=""),"",H33/AC33-1)
A34: 3102220102522 | B34: Крестовина карданного вала | D34: УАЗ/ГАЗ | E34: Подвеска | H34: 10000 | I34: 28 | K34: =I34-J34 -> 28 | L34: =K34*H34 -> 280000 | M34: =IF(A34="","",H34*J34) -> 0 | N34: =IF(A34="","",G34*J34) -> 0 | O34: =IF(A34="","",M34-N34) -> 0 | Q34: 3102220102522 | V34: 664 | AB34: =SUMPRODUCT(--(R34:AA34>0),'Настройки цен'!$B$12:$K$12) -> 1 | AC34: =IF(AB34=0,"",SUMPRODUCT(R34:AA34,'Настройки цен'!$B$11:$K$11,'Настройки цен'!$B$12:$K$12)/AB34) -> 3519.2 | AE34: =IF(AD34<>"",AD34,IFERROR(IF(INDEX('Настройки цен'!$B$17:$B$24,MATCH(E34,'Настройки цен'!$A$17:$A$24,0))="",'Настройки цен'!$B$5,INDEX('Настройки цен'!$B$17:$B$24,MATCH(E34,'Настройки цен'!$A$17:$A$24,0))),'Настройки цен'!$B$5)) -> 0 | AF34: =IF(AC34="","",ROUND(AC34*(1+AE34)/'Настройки цен'!$B$6,0)*'Настройки цен'!$B$6) -> 3500 | AG34: =IF(OR(AC34="",H34=""),"",H34/AC34-1) -> 1.8415549 | AH34: detaliuaz.ru: крестовина кардана УАЗ/ГАЗ d30 «Автомагнат» 664 ₽ (аналог, не оригинал). Наша цена 10 000 ₸ — сильно выше рынка РФ.
A35: 452002304112 | B35: муфта скользящая фланца | D35: УАЗ | E35: Подвеска | H35: 13000 | I35: 5 | K35: =I35-J35 -> 5 | L35: =K35*H35 -> 65000 | M35: =IF(A35="","",H35*J35) -> 0 | N35: =IF(A35="","",G35*J35) -> 0 | O35: =IF(A35="","",M35-N35) -> 0 | Q35: 452002304112 | AB35: =SUMPRODUCT(--(R35:AA35>0),'Настройки цен'!$B$12:$K$12) -> 0 | AC35: =IF(AB35=0,"",SUMPRODUCT(R35:AA35,'Настройки цен'!$B$11:$K$11,'Настройки цен'!$B$12:$K$12)/AB35) | AE35: =IF(AD35<>"",AD35,IFERROR(IF(INDEX('Настройки цен'!$B$17:$B$24,MATCH(E35,'Настройки цен'!$A$17:$A$24,0))="",'Настройки цен'!$B$5,INDEX('Настройки цен'!$B$17:$B$24,MATCH(E35,'Настройки цен'!$A$17:$A$24,0))),'Настройки цен'!$B$5)) -> 0 | AF35: =IF(AC35="","",ROUND(AC35*(1+AE35)/'Настройки цен'!$B$6,0)*'Настройки цен'!$B$6) | AG35: =IF(OR(AC35="",H35=""),"",H35/AC35-1)
A36: 315120230440003 | B36: Хаб Noname (1шт) | D36: УАЗ | E36: Подвеска | H36: 20000 | I36: 2 | K36: =I36-J36 -> 2 | L36: =K36*H36 -> 40000 | M36: =IF(A36="","",H36*J36) -> 0 | N36: =IF(A36="","",G36*J36) -> 0 | O36: =IF(A36="","",M36-N36) -> 0 | Q36: 315120230440003 | AB36: =SUMPRODUCT(--(R36:AA36>0),'Настройки цен'!$B$12:$K$12) -> 0 | AC36: =IF(AB36=0,"",SUMPRODUCT(R36:AA36,'Настройки цен'!$B$11:$K$11,'Настройки цен'!$B$12:$K$12)/AB36) | AE36: =IF(AD36<>"",AD36,IFERROR(IF(INDEX('Настройки цен'!$B$17:$B$24,MATCH(E36,'Настройки цен'!$A$17:$A$24,0))="",'Настройки цен'!$B$5,INDEX('Настройки цен'!$B$17:$B$24,MATCH(E36,'Настройки цен'!$A$17:$A$24,0))),'Настройки цен'!$B$5)) -> 0 | AF36: =IF(AC36="","",ROUND(AC36*(1+AE36)/'Настройки цен'!$B$6,0)*'Настройки цен'!$B$6) | AG36: =IF(OR(AC36="",H36=""),"",H36/AC36-1)
A37: 374100380203400 | B37: Шестерня привода спидометра 16-17 зубов | D37: Уаз | E37: Другое | H37: 7000 | I37: 5 | K37: =I37-J37 -> 5 | L37: =K37*H37 -> 35000 | M37: =IF(A37="","",H37*J37) -> 0 | N37: =IF(A37="","",G37*J37) -> 0 | O37: =IF(A37="","",M37-N37) -> 0 | Q37: 374100380203400 | AB37: =SUMPRODUCT(--(R37:AA37>0),'Настройки цен'!$B$12:$K$12) -> 0 | AC37: =IF(AB37=0,"",SUMPRODUCT(R37:AA37,'Настройки цен'!$B$11:$K$11,'Настройки цен'!$B$12:$K$12)/AB37) | AE37: =IF(AD37<>"",AD37,IFERROR(IF(INDEX('Настройки цен'!$B$17:$B$24,MATCH(E37,'Настройки цен'!$A$17:$A$24,0))="",'Настройки цен'!$B$5,INDEX('Настройки цен'!$B$17:$B$24,MATCH(E37,'Настройки цен'!$A$17:$A$24,0))),'Настройки цен'!$B$5)) -> 0 | AF37: =IF(AC37="","",ROUND(AC37*(1+AE37)/'Настройки цен'!$B$6,0)*'Настройки цен'!$B$6) | AG37: =IF(OR(AC37="",H37=""),"",H37/AC37-1)
A38: 33073802034 | B38: Шестерня привода спидометра 21 зуб | D38: ГАЗ | E38: Другое | H38: 10000 | I38: 5 | K38: =I38-J38 -> 5 | L38: =K38*H38 -> 50000 | M38: =IF(A38="","",H38*J38) -> 0 | N38: =IF(A38="","",G38*J38) -> 0 | O38: =IF(A38="","",M38-N38) -> 0 | Q38: 33073802034 | AB38: =SUMPRODUCT(--(R38:AA38>0),'Настройки цен'!$B$12:$K$12) -> 0 | AC38: =IF(AB38=0,"",SUMPRODUCT(R38:AA38,'Настройки цен'!$B$11:$K$11,'Настройки цен'!$B$12:$K$12)/AB38) | AE38: =IF(AD38<>"",AD38,IFERROR(IF(INDEX('Настройки цен'!$B$17:$B$24,MATCH(E38,'Настройки цен'!$A$17:$A$24,0))="",'Настройки цен'!$B$5,INDEX('Настройки цен'!$B$17:$B$24,MATCH(E38,'Настройки цен'!$A$17:$A$24,0))),'Настройки цен'!$B$5)) -> 0 | AF38: =IF(AC38="","",ROUND(AC38*(1+AE38)/'Настройки цен'!$B$6,0)*'Настройки цен'!$B$6) | AG38: =IF(OR(AC38="",H38=""),"",H38/AC38-1)
A39: 374100170125000 | B39: Вал промежуточный | D39: УАЗ | E39: Подвеска | H39: 22000 | I39: 1 | K39: =I39-J39 -> 1 | L39: =K39*H39 -> 22000 | M39: =IF(A39="","",H39*J39) -> 0 | N39: =IF(A39="","",G39*J39) -> 0 | O39: =IF(A39="","",M39-N39) -> 0 | Q39: 374100170125000 | AB39: =SUMPRODUCT(--(R39:AA39>0),'Настройки цен'!$B$12:$K$12) -> 0 | AC39: =IF(AB39=0,"",SUMPRODUCT(R39:AA39,'Настройки цен'!$B$11:$K$11,'Настройки цен'!$B$12:$K$12)/AB39) | AE39: =IF(AD39<>"",AD39,IFERROR(IF(INDEX('Настройки цен'!$B$17:$B$24,MATCH(E39,'Настройки цен'!$A$17:$A$24,0))="",'Настройки цен'!$B$5,INDEX('Настройки цен'!$B$17:$B$24,MATCH(E39,'Настройки цен'!$A$17:$A$24,0))),'Настройки цен'!$B$5)) -> 0 | AF39: =IF(AC39="","",ROUND(AC39*(1+AE39)/'Настройки цен'!$B$6,0)*'Настройки цен'!$B$6) | AG39: =IF(OR(AC39="",H39=""),"",H39/AC39-1)
A40: 42x68x10x15.5 | B40: Сальник хвостовика и РК | D40: УАЗ | E40: Подвеска | H40: 1500 | I40: 17 | K40: =I40-J40 -> 17 | L40: =K40*H40 -> 25500 | M40: =IF(A40="","",H40*J40) -> 0 | N40: =IF(A40="","",G40*J40) -> 0 | O40: =IF(A40="","",M40-N40) -> 0 | Q40: 42x68x10x15.5 | AB40: =SUMPRODUCT(--(R40:AA40>0),'Настройки цен'!$B$12:$K$12) -> 0 | AC40: =IF(AB40=0,"",SUMPRODUCT(R40:AA40,'Настройки цен'!$B$11:$K$11,'Настройки цен'!$B$12:$K$12)/AB40) | AE40: =IF(AD40<>"",AD40,IFERROR(IF(INDEX('Настройки цен'!$B$17:$B$24,MATCH(E40,'Настройки цен'!$A$17:$A$24,0))="",'Настройки цен'!$B$5,INDEX('Настройки цен'!$B$17:$B$24,MATCH(E40,'Настройки цен'!$A$17:$A$24,0))),'Настройки цен'!$B$5)) -> 0 | AF40: =IF(AC40="","",ROUND(AC40*(1+AE40)/'Настройки цен'!$B$6,0)*'Настройки цен'!$B$6) | AG40: =IF(OR(AC40="",H40=""),"",H40/AC40-1)
A41: 4691701164 | B41: Кольцо синхронизатора н/о | D41: УАЗ | E41: Подвеска | H41: 6000 | I41: 28 | K41: =I41-J41 -> 28 | L41: =K41*H41 -> 168000 | M41: =IF(A41="","",H41*J41) -> 0 | N41: =IF(A41="","",G41*J41) -> 0 | O41: =IF(A41="","",M41-N41) -> 0 | Q41: 4691701164 | AB41: =SUMPRODUCT(--(R41:AA41>0),'Настройки цен'!$B$12:$K$12) -> 0 | AC41: =IF(AB41=0,"",SUMPRODUCT(R41:AA41,'Настройки цен'!$B$11:$K$11,'Настройки цен'!$B$12:$K$12)/AB41) | AE41: =IF(AD41<>"",AD41,IFERROR(IF(INDEX('Настройки цен'!$B$17:$B$24,MATCH(E41,'Настройки цен'!$A$17:$A$24,0))="",'Настройки цен'!$B$5,INDEX('Настройки цен'!$B$17:$B$24,MATCH(E41,'Настройки цен'!$A$17:$A$24,0))),'Настройки цен'!$B$5)) -> 0 | AF41: =IF(AC41="","",ROUND(AC41*(1+AE41)/'Настройки цен'!$B$6,0)*'Настройки цен'!$B$6) | AG41: =IF(OR(AC41="",H41=""),"",H41/AC41-1)
B42: Ремкомплект суппорта | D42: УАЗ | E42: Тормоза | H42: 3000 | I42: 9 | K42: =I42-J42 -> 9 | L42: =K42*H42 -> 27000 | M42: =IF(A42="","",H42*J42) | N42: =IF(A42="","",G42*J42) | O42: =IF(A42="","",M42-N42) | AB42: =SUMPRODUCT(--(R42:AA42>0),'Настройки цен'!$B$12:$K$12) -> 0 | AC42: =IF(AB42=0,"",SUMPRODUCT(R42:AA42,'Настройки цен'!$B$11:$K$11,'Настройки цен'!$B$12:$K$12)/AB42) | AE42: =IF(AD42<>"",AD42,IFERROR(IF(INDEX('Настройки цен'!$B$17:$B$24,MATCH(E42,'Настройки цен'!$A$17:$A$24,0))="",'Настройки цен'!$B$5,INDEX('Настройки цен'!$B$17:$B$24,MATCH(E42,'Настройки цен'!$A$17:$A$24,0))),'Настройки цен'!$B$5)) -> 0 | AF42: =IF(AC42="","",ROUND(AC42*(1+AE42)/'Настройки цен'!$B$6,0)*'Настройки цен'!$B$6) | AG42: =IF(OR(AC42="",H42=""),"",H42/AC42-1)
A43: 57707 | B43: Подшипник ведущей шестерни главной передачи | D43: УАЗ | E43: Подвеска | H43: 9000 | I43: 5 | K43: =I43-J43 -> 5 | L43: =K43*H43 -> 45000 | M43: =IF(A43="","",H43*J43) -> 0 | N43: =IF(A43="","",G43*J43) -> 0 | O43: =IF(A43="","",M43-N43) -> 0 | Q43: 57707 | AB43: =SUMPRODUCT(--(R43:AA43>0),'Настройки цен'!$B$12:$K$12) -> 0 | AC43: =IF(AB43=0,"",SUMPRODUCT(R43:AA43,'Настройки цен'!$B$11:$K$11,'Настройки цен'!$B$12:$K$12)/AB43) | AE43: =IF(AD43<>"",AD43,IFERROR(IF(INDEX('Настройки цен'!$B$17:$B$24,MATCH(E43,'Настройки цен'!$A$17:$A$24,0))="",'Настройки цен'!$B$5,INDEX('Настройки цен'!$B$17:$B$24,MATCH(E43,'Настройки цен'!$A$17:$A$24,0))),'Настройки цен'!$B$5)) -> 0 | AF43: =IF(AC43="","",ROUND(AC43*(1+AE43)/'Настройки цен'!$B$6,0)*'Настройки цен'!$B$6) | AG43: =IF(OR(AC43="",H43=""),"",H43/AC43-1)
A44: 451501701040 | B44: крышка подшипника первичного вала КПП | D44: Уаз | E44: Подвеска | H44: 10000 | I44: 13 | K44: =I44-J44 -> 13 | L44: =K44*H44 -> 130000 | M44: =IF(A44="","",H44*J44) -> 0 | N44: =IF(A44="","",G44*J44) -> 0 | O44: =IF(A44="","",M44-N44) -> 0 | Q44: 451501701040 | AB44: =SUMPRODUCT(--(R44:AA44>0),'Настройки цен'!$B$12:$K$12) -> 0 | AC44: =IF(AB44=0,"",SUMPRODUCT(R44:AA44,'Настройки цен'!$B$11:$K$11,'Настройки цен'!$B$12:$K$12)/AB44) | AE44: =IF(AD44<>"",AD44,IFERROR(IF(INDEX('Настройки цен'!$B$17:$B$24,MATCH(E44,'Настройки цен'!$A$17:$A$24,0))="",'Настройки цен'!$B$5,INDEX('Настройки цен'!$B$17:$B$24,MATCH(E44,'Настройки цен'!$A$17:$A$24,0))),'Настройки цен'!$B$5)) -> 0 | AF44: =IF(AC44="","",ROUND(AC44*(1+AE44)/'Настройки цен'!$B$6,0)*'Настройки цен'!$B$6) | AG44: =IF(OR(AC44="",H44=""),"",H44/AC44-1)
B45: Корпус поворотного кулака правый | D45: УАЗ | E45: Подвеска | H45: 60000 | I45: 1 | K45: =I45-J45 -> 1 | L45: =K45*H45 -> 60000 | M45: =IF(A45="","",H45*J45) | N45: =IF(A45="","",G45*J45) | O45: =IF(A45="","",M45-N45) | AB45: =SUMPRODUCT(--(R45:AA45>0),'Настройки цен'!$B$12:$K$12) -> 0 | AC45: =IF(AB45=0,"",SUMPRODUCT(R45:AA45,'Настройки цен'!$B$11:$K$11,'Настройки цен'!$B$12:$K$12)/AB45) | AE45: =IF(AD45<>"",AD45,IFERROR(IF(INDEX('Настройки цен'!$B$17:$B$24,MATCH(E45,'Настройки цен'!$A$17:$A$24,0))="",'Настройки цен'!$B$5,INDEX('Настройки цен'!$B$17:$B$24,MATCH(E45,'Настройки цен'!$A$17:$A$24,0))),'Настройки цен'!$B$5)) -> 0 | AF45: =IF(AC45="","",ROUND(AC45*(1+AE45)/'Настройки цен'!$B$6,0)*'Настройки цен'!$B$6) | AG45: =IF(OR(AC45="",H45=""),"",H45/AC45-1)
B46: Корпус поворотного кулака левый | D46: УАЗ | E46: Подвеска | H46: 60000 | I46: 1 | K46: =I46-J46 -> 1 | L46: =K46*H46 -> 60000 | M46: =IF(A46="","",H46*J46) | N46: =IF(A46="","",G46*J46) | O46: =IF(A46="","",M46-N46) | AB46: =SUMPRODUCT(--(R46:AA46>0),'Настройки цен'!$B$12:$K$12) -> 0 | AC46: =IF(AB46=0,"",SUMPRODUCT(R46:AA46,'Настройки цен'!$B$11:$K$11,'Настройки цен'!$B$12:$K$12)/AB46) | AE46: =IF(AD46<>"",AD46,IFERROR(IF(INDEX('Настройки цен'!$B$17:$B$24,MATCH(E46,'Настройки цен'!$A$17:$A$24,0))="",'Настройки цен'!$B$5,INDEX('Настройки цен'!$B$17:$B$24,MATCH(E46,'Настройки цен'!$A$17:$A$24,0))),'Настройки цен'!$B$5)) -> 0 | AF46: =IF(AC46="","",ROUND(AC46*(1+AE46)/'Настройки цен'!$B$6,0)*'Настройки цен'!$B$6) | AG46: =IF(OR(AC46="",H46=""),"",H46/AC46-1)
B47: Рулевой наконечник | D47: УАЗ | E47: Подвеска | H47: 7000 | I47: 24 | K47: =I47-J47 -> 24 | L47: =K47*H47 -> 168000 | M47: =IF(A47="","",H47*J47) | N47: =IF(A47="","",G47*J47) | O47: =IF(A47="","",M47-N47) | AB47: =SUMPRODUCT(--(R47:AA47>0),'Настройки цен'!$B$12:$K$12) -> 0 | AC47: =IF(AB47=0,"",SUMPRODUCT(R47:AA47,'Настройки цен'!$B$11:$K$11,'Настройки цен'!$B$12:$K$12)/AB47) | AE47: =IF(AD47<>"",AD47,IFERROR(IF(INDEX('Настройки цен'!$B$17:$B$24,MATCH(E47,'Настройки цен'!$A$17:$A$24,0))="",'Настройки цен'!$B$5,INDEX('Настройки цен'!$B$17:$B$24,MATCH(E47,'Настройки цен'!$A$17:$A$24,0))),'Настройки цен'!$B$5)) -> 0 | AF47: =IF(AC47="","",ROUND(AC47*(1+AE47)/'Настройки цен'!$B$6,0)*'Настройки цен'!$B$6) | AG47: =IF(OR(AC47="",H47=""),"",H47/AC47-1)
B48: Рулевой наконечник | D48: ГАЗ | E48: Подвеска | H48: 7000 | I48: 1 | K48: =I48-J48 -> 1 | L48: =K48*H48 -> 7000 | M48: =IF(A48="","",H48*J48) | N48: =IF(A48="","",G48*J48) | O48: =IF(A48="","",M48-N48) | AB48: =SUMPRODUCT(--(R48:AA48>0),'Настройки цен'!$B$12:$K$12) -> 0 | AC48: =IF(AB48=0,"",SUMPRODUCT(R48:AA48,'Настройки цен'!$B$11:$K$11,'Настройки цен'!$B$12:$K$12)/AB48) | AE48: =IF(AD48<>"",AD48,IFERROR(IF(INDEX('Настройки цен'!$B$17:$B$24,MATCH(E48,'Настройки цен'!$A$17:$A$24,0))="",'Настройки цен'!$B$5,INDEX('Настройки цен'!$B$17:$B$24,MATCH(E48,'Настройки цен'!$A$17:$A$24,0))),'Настройки цен'!$B$5)) -> 0 | AF48: =IF(AC48="","",ROUND(AC48*(1+AE48)/'Настройки цен'!$B$6,0)*'Настройки цен'!$B$6) | AG48: =IF(OR(AC48="",H48=""),"",H48/AC48-1)
B49: Кольцо синхронизатора с/о | D49: УАЗ | E49: Подвеска | H49: 6000 | I49: 14 | K49: =I49-J49 -> 14 | L49: =K49*H49 -> 84000 | M49: =IF(A49="","",H49*J49) | N49: =IF(A49="","",G49*J49) | O49: =IF(A49="","",M49-N49) | AB49: =SUMPRODUCT(--(R49:AA49>0),'Настройки цен'!$B$12:$K$12) -> 0 | AC49: =IF(AB49=0,"",SUMPRODUCT(R49:AA49,'Настройки цен'!$B$11:$K$11,'Настройки цен'!$B$12:$K$12)/AB49) | AE49: =IF(AD49<>"",AD49,IFERROR(IF(INDEX('Настройки цен'!$B$17:$B$24,MATCH(E49,'Настройки цен'!$A$17:$A$24,0))="",'Настройки цен'!$B$5,INDEX('Настройки цен'!$B$17:$B$24,MATCH(E49,'Настройки цен'!$A$17:$A$24,0))),'Настройки цен'!$B$5)) -> 0 | AF49: =IF(AC49="","",ROUND(AC49*(1+AE49)/'Настройки цен'!$B$6,0)*'Настройки цен'!$B$6) | AG49: =IF(OR(AC49="",H49=""),"",H49/AC49-1)
B50: Сальник коленвала | D50: ГАЗ | E50: Двигатель | H50: 1500 | I50: 6 | K50: =I50-J50 -> 6 | L50: =K50*H50 -> 9000 | M50: =IF(A50="","",H50*J50) | N50: =IF(A50="","",G50*J50) | O50: =IF(A50="","",M50-N50) | AB50: =SUMPRODUCT(--(R50:AA50>0),'Настройки цен'!$B$12:$K$12) -> 0 | AC50: =IF(AB50=0,"",SUMPRODUCT(R50:AA50,'Настройки цен'!$B$11:$K$11,'Настройки цен'!$B$12:$K$12)/AB50) | AE50: =IF(AD50<>"",AD50,IFERROR(IF(INDEX('Настройки цен'!$B$17:$B$24,MATCH(E50,'Настройки цен'!$A$17:$A$24,0))="",'Настройки цен'!$B$5,INDEX('Настройки цен'!$B$17:$B$24,MATCH(E50,'Настройки цен'!$A$17:$A$24,0))),'Настройки цен'!$B$5)) -> 0 | AF50: =IF(AC50="","",ROUND(AC50*(1+AE50)/'Настройки цен'!$B$6,0)*'Настройки цен'!$B$6) | AG50: =IF(OR(AC50="",H50=""),"",H50/AC50-1)
A51: 37413103038 | B51: Сальник ступицы колеса | D51: УАЗ | E51: Подвеска | H51: 1500 | I51: 8 | K51: =I51-J51 -> 8 | L51: =K51*H51 -> 12000 | M51: =IF(A51="","",H51*J51) -> 0 | N51: =IF(A51="","",G51*J51) -> 0 | O51: =IF(A51="","",M51-N51) -> 0 | Q51: 37413103038 | AB51: =SUMPRODUCT(--(R51:AA51>0),'Настройки цен'!$B$12:$K$12) -> 0 | AC51: =IF(AB51=0,"",SUMPRODUCT(R51:AA51,'Настройки цен'!$B$11:$K$11,'Настройки цен'!$B$12:$K$12)/AB51) | AE51: =IF(AD51<>"",AD51,IFERROR(IF(INDEX('Настройки цен'!$B$17:$B$24,MATCH(E51,'Настройки цен'!$A$17:$A$24,0))="",'Настройки цен'!$B$5,INDEX('Настройки цен'!$B$17:$B$24,MATCH(E51,'Настройки цен'!$A$17:$A$24,0))),'Настройки цен'!$B$5)) -> 0 | AF51: =IF(AC51="","",ROUND(AC51*(1+AE51)/'Настройки цен'!$B$6,0)*'Настройки цен'!$B$6) | AG51: =IF(OR(AC51="",H51=""),"",H51/AC51-1)
B52: Опора шкворня | D52: УАЗ | E52: Подвеска | H52: 2000 | I52: 12 | K52: =I52-J52 -> 12 | L52: =K52*H52 -> 24000 | M52: =IF(A52="","",H52*J52) | N52: =IF(A52="","",G52*J52) | O52: =IF(A52="","",M52-N52) | AB52: =SUMPRODUCT(--(R52:AA52>0),'Настройки цен'!$B$12:$K$12) -> 0 | AC52: =IF(AB52=0,"",SUMPRODUCT(R52:AA52,'Настройки цен'!$B$11:$K$11,'Настройки цен'!$B$12:$K$12)/AB52) | AE52: =IF(AD52<>"",AD52,IFERROR(IF(INDEX('Настройки цен'!$B$17:$B$24,MATCH(E52,'Настройки цен'!$A$17:$A$24,0))="",'Настройки цен'!$B$5,INDEX('Настройки цен'!$B$17:$B$24,MATCH(E52,'Настройки цен'!$A$17:$A$24,0))),'Настройки цен'!$B$5)) -> 0 | AF52: =IF(AC52="","",ROUND(AC52*(1+AE52)/'Настройки цен'!$B$6,0)*'Настройки цен'!$B$6) | AG52: =IF(OR(AC52="",H52=""),"",H52/AC52-1)
B53: Ручка двери | D53: УАЗ | E53: Кузов | H53: 5000 | I53: 3 | K53: =I53-J53 -> 3 | L53: =K53*H53 -> 15000 | M53: =IF(A53="","",H53*J53) | N53: =IF(A53="","",G53*J53) | O53: =IF(A53="","",M53-N53) | AB53: =SUMPRODUCT(--(R53:AA53>0),'Настройки цен'!$B$12:$K$12) -> 0 | AC53: =IF(AB53=0,"",SUMPRODUCT(R53:AA53,'Настройки цен'!$B$11:$K$11,'Настройки цен'!$B$12:$K$12)/AB53) | AE53: =IF(AD53<>"",AD53,IFERROR(IF(INDEX('Настройки цен'!$B$17:$B$24,MATCH(E53,'Настройки цен'!$A$17:$A$24,0))="",'Настройки цен'!$B$5,INDEX('Настройки цен'!$B$17:$B$24,MATCH(E53,'Настройки цен'!$A$17:$A$24,0))),'Настройки цен'!$B$5)) -> 0 | AF53: =IF(AC53="","",ROUND(AC53*(1+AE53)/'Настройки цен'!$B$6,0)*'Настройки цен'!$B$6) | AG53: =IF(OR(AC53="",H53=""),"",H53/AC53-1)
A54: 316300811001007 | B54: Задняя печка патриот | D54: Уаз | E54: Электрика | H54: 65000 | I54: 1 | K54: =I54-J54 -> 1 | L54: =K54*H54 -> 65000 | M54: =IF(A54="","",H54*J54) -> 0 | N54: =IF(A54="","",G54*J54) -> 0 | O54: =IF(A54="","",M54-N54) -> 0 | Q54: 316300811001007 | AB54: =SUMPRODUCT(--(R54:AA54>0),'Настройки цен'!$B$12:$K$12) -> 0 | AC54: =IF(AB54=0,"",SUMPRODUCT(R54:AA54,'Настройки цен'!$B$11:$K$11,'Настройки цен'!$B$12:$K$12)/AB54) | AE54: =IF(AD54<>"",AD54,IFERROR(IF(INDEX('Настройки цен'!$B$17:$B$24,MATCH(E54,'Настройки цен'!$A$17:$A$24,0))="",'Настройки цен'!$B$5,INDEX('Настройки цен'!$B$17:$B$24,MATCH(E54,'Настройки цен'!$A$17:$A$24,0))),'Настройки цен'!$B$5)) -> 0 | AF54: =IF(AC54="","",ROUND(AC54*(1+AE54)/'Настройки цен'!$B$6,0)*'Настройки цен'!$B$6) | AG54: =IF(OR(AC54="",H54=""),"",H54/AC54-1)
A55: 310291117010 | B55: Топливный фильтр | D55: УАЗ/ГАЗ | E55: Фильтры | H55: 4000 | I55: 4 | K55: =I55-J55 -> 4 | L55: =K55*H55 -> 16000 | M55: =IF(A55="","",H55*J55) -> 0 | N55: =IF(A55="","",G55*J55) -> 0 | O55: =IF(A55="","",M55-N55) -> 0 | Q55: 310291117010 | AB55: =SUMPRODUCT(--(R55:AA55>0),'Настройки цен'!$B$12:$K$12) -> 0 | AC55: =IF(AB55=0,"",SUMPRODUCT(R55:AA55,'Настройки цен'!$B$11:$K$11,'Настройки цен'!$B$12:$K$12)/AB55) | AE55: =IF(AD55<>"",AD55,IFERROR(IF(INDEX('Настройки цен'!$B$17:$B$24,MATCH(E55,'Настройки цен'!$A$17:$A$24,0))="",'Настройки цен'!$B$5,INDEX('Настройки цен'!$B$17:$B$24,MATCH(E55,'Настройки цен'!$A$17:$A$24,0))),'Настройки цен'!$B$5)) -> 0 | AF55: =IF(AC55="","",ROUND(AC55*(1+AE55)/'Настройки цен'!$B$6,0)*'Настройки цен'!$B$6) | AG55: =IF(OR(AC55="",H55=""),"",H55/AC55-1)
A56: 24100010202 | B56: Вкладыши шатунные 0.25 | D56: УАЗ/ГАЗ | E56: Двигатель | H56: 10000 | I56: 3 | K56: =I56-J56 -> 3 | L56: =K56*H56 -> 30000 | M56: =IF(A56="","",H56*J56) -> 0 | N56: =IF(A56="","",G56*J56) -> 0 | O56: =IF(A56="","",M56-N56) -> 0 | Q56: 24100010202 | AB56: =SUMPRODUCT(--(R56:AA56>0),'Настройки цен'!$B$12:$K$12) -> 0 | AC56: =IF(AB56=0,"",SUMPRODUCT(R56:AA56,'Настройки цен'!$B$11:$K$11,'Настройки цен'!$B$12:$K$12)/AB56) | AE56: =IF(AD56<>"",AD56,IFERROR(IF(INDEX('Настройки цен'!$B$17:$B$24,MATCH(E56,'Настройки цен'!$A$17:$A$24,0))="",'Настройки цен'!$B$5,INDEX('Настройки цен'!$B$17:$B$24,MATCH(E56,'Настройки цен'!$A$17:$A$24,0))),'Настройки цен'!$B$5)) -> 0 | AF56: =IF(AC56="","",ROUND(AC56*(1+AE56)/'Настройки цен'!$B$6,0)*'Настройки цен'!$B$6) | AG56: =IF(OR(AC56="",H56=""),"",H56/AC56-1)
A57: 24100010231 | B57: Вкладыши коренные 0.50 | D57: УАЗ/ГАЗ | E57: Двигатель | H57: 10000 | I57: 2 | K57: =I57-J57 -> 2 | L57: =K57*H57 -> 20000 | M57: =IF(A57="","",H57*J57) -> 0 | N57: =IF(A57="","",G57*J57) -> 0 | O57: =IF(A57="","",M57-N57) -> 0 | Q57: 24100010231 | AB57: =SUMPRODUCT(--(R57:AA57>0),'Настройки цен'!$B$12:$K$12) -> 0 | AC57: =IF(AB57=0,"",SUMPRODUCT(R57:AA57,'Настройки цен'!$B$11:$K$11,'Настройки цен'!$B$12:$K$12)/AB57) | AE57: =IF(AD57<>"",AD57,IFERROR(IF(INDEX('Настройки цен'!$B$17:$B$24,MATCH(E57,'Настройки цен'!$A$17:$A$24,0))="",'Настройки цен'!$B$5,INDEX('Настройки цен'!$B$17:$B$24,MATCH(E57,'Настройки цен'!$A$17:$A$24,0))),'Настройки цен'!$B$5)) -> 0 | AF57: =IF(AC57="","",ROUND(AC57*(1+AE57)/'Настройки цен'!$B$6,0)*'Настройки цен'!$B$6) | AG57: =IF(OR(AC57="",H57=""),"",H57/AC57-1)
A58: 241000104 | B58: Вкладыши шатунные 0.75 | D58: УАЗ/ГАЗ | E58: Двигатель | H58: 10000 | I58: 1 | K58: =I58-J58 -> 1 | L58: =K58*H58 -> 10000 | M58: =IF(A58="","",H58*J58) -> 0 | N58: =IF(A58="","",G58*J58) -> 0 | O58: =IF(A58="","",M58-N58) -> 0 | Q58: 241000104 | AB58: =SUMPRODUCT(--(R58:AA58>0),'Настройки цен'!$B$12:$K$12) -> 0 | AC58: =IF(AB58=0,"",SUMPRODUCT(R58:AA58,'Настройки цен'!$B$11:$K$11,'Настройки цен'!$B$12:$K$12)/AB58) | AE58: =IF(AD58<>"",AD58,IFERROR(IF(INDEX('Настройки цен'!$B$17:$B$24,MATCH(E58,'Настройки цен'!$A$17:$A$24,0))="",'Настройки цен'!$B$5,INDEX('Настройки цен'!$B$17:$B$24,MATCH(E58,'Настройки цен'!$A$17:$A$24,0))),'Настройки цен'!$B$5)) -> 0 | AF58: =IF(AC58="","",ROUND(AC58*(1+AE58)/'Настройки цен'!$B$6,0)*'Настройки цен'!$B$6) | AG58: =IF(OR(AC58="",H58=""),"",H58/AC58-1)
A59: 24100010010 | B59: Поршневые кольца (комплект) | D59: ГАЗ | E59: Двигатель | H59: 8000 | I59: 7 | K59: =I59-J59 -> 7 | L59: =K59*H59 -> 56000 | M59: =IF(A59="","",H59*J59) -> 0 | N59: =IF(A59="","",G59*J59) -> 0 | O59: =IF(A59="","",M59-N59) -> 0 | Q59: 24100010010 | AB59: =SUMPRODUCT(--(R59:AA59>0),'Настройки цен'!$B$12:$K$12) -> 0 | AC59: =IF(AB59=0,"",SUMPRODUCT(R59:AA59,'Настройки цен'!$B$11:$K$11,'Настройки цен'!$B$12:$K$12)/AB59) | AE59: =IF(AD59<>"",AD59,IFERROR(IF(INDEX('Настройки цен'!$B$17:$B$24,MATCH(E59,'Настройки цен'!$A$17:$A$24,0))="",'Настройки цен'!$B$5,INDEX('Настройки цен'!$B$17:$B$24,MATCH(E59,'Настройки цен'!$A$17:$A$24,0))),'Настройки цен'!$B$5)) -> 0 | AF59: =IF(AC59="","",ROUND(AC59*(1+AE59)/'Настройки цен'!$B$6,0)*'Настройки цен'!$B$6) | AG59: =IF(OR(AC59="",H59=""),"",H59/AC59-1)
A60: 24501601094 | B60: Рычаг нажимного диска | D60: УАЗ/ГАЗ | E60: Подвеска | H60: 6000 | I60: 11 | K60: =I60-J60 -> 11 | L60: =K60*H60 -> 66000 | M60: =IF(A60="","",H60*J60) -> 0 | N60: =IF(A60="","",G60*J60) -> 0 | O60: =IF(A60="","",M60-N60) -> 0 | Q60: 24501601094 | AB60: =SUMPRODUCT(--(R60:AA60>0),'Настройки цен'!$B$12:$K$12) -> 0 | AC60: =IF(AB60=0,"",SUMPRODUCT(R60:AA60,'Настройки цен'!$B$11:$K$11,'Настройки цен'!$B$12:$K$12)/AB60) | AE60: =IF(AD60<>"",AD60,IFERROR(IF(INDEX('Настройки цен'!$B$17:$B$24,MATCH(E60,'Настройки цен'!$A$17:$A$24,0))="",'Настройки цен'!$B$5,INDEX('Настройки цен'!$B$17:$B$24,MATCH(E60,'Настройки цен'!$A$17:$A$24,0))),'Настройки цен'!$B$5)) -> 0 | AF60: =IF(AC60="","",ROUND(AC60*(1+AE60)/'Настройки цен'!$B$6,0)*'Настройки цен'!$B$6) | AG60: =IF(OR(AC60="",H60=""),"",H60/AC60-1)
B61: Шпилька колеса | D61: УАЗ | E61: Подвеска | H61: 500 | I61: 143 | K61: =I61-J61 -> 143 | L61: =K61*H61 -> 71500 | M61: =IF(A61="","",H61*J61) | N61: =IF(A61="","",G61*J61) | O61: =IF(A61="","",M61-N61) | AB61: =SUMPRODUCT(--(R61:AA61>0),'Настройки цен'!$B$12:$K$12) -> 0 | AC61: =IF(AB61=0,"",SUMPRODUCT(R61:AA61,'Настройки цен'!$B$11:$K$11,'Настройки цен'!$B$12:$K$12)/AB61) | AE61: =IF(AD61<>"",AD61,IFERROR(IF(INDEX('Настройки цен'!$B$17:$B$24,MATCH(E61,'Настройки цен'!$A$17:$A$24,0))="",'Настройки цен'!$B$5,INDEX('Настройки цен'!$B$17:$B$24,MATCH(E61,'Настройки цен'!$A$17:$A$24,0))),'Настройки цен'!$B$5)) -> 0 | AF61: =IF(AC61="","",ROUND(AC61*(1+AE61)/'Настройки цен'!$B$6,0)*'Настройки цен'!$B$6) | AG61: =IF(OR(AC61="",H61=""),"",H61/AC61-1)
B62: Крышка стартера | D62: УАЗ/ГАЗ | E62: Двигатель | H62: 7000 | I62: 7 | K62: =I62-J62 -> 7 | L62: =K62*H62 -> 49000 | M62: =IF(A62="","",H62*J62) | N62: =IF(A62="","",G62*J62) | O62: =IF(A62="","",M62-N62) | AB62: =SUMPRODUCT(--(R62:AA62>0),'Настройки цен'!$B$12:$K$12) -> 0 | AC62: =IF(AB62=0,"",SUMPRODUCT(R62:AA62,'Настройки цен'!$B$11:$K$11,'Настройки цен'!$B$12:$K$12)/AB62) | AE62: =IF(AD62<>"",AD62,IFERROR(IF(INDEX('Настройки цен'!$B$17:$B$24,MATCH(E62,'Настройки цен'!$A$17:$A$24,0))="",'Настройки цен'!$B$5,INDEX('Настройки цен'!$B$17:$B$24,MATCH(E62,'Настройки цен'!$A$17:$A$24,0))),'Настройки цен'!$B$5)) -> 0 | AF62: =IF(AC62="","",ROUND(AC62*(1+AE62)/'Настройки цен'!$B$6,0)*'Настройки цен'!$B$6) | AG62: =IF(OR(AC62="",H62=""),"",H62/AC62-1)
B63: Тормозной шланг длинный | D63: УАЗ | E63: Тормоза | H63: 3000 | I63: 22 | K63: =I63-J63 -> 22 | L63: =K63*H63 -> 66000 | M63: =IF(A63="","",H63*J63) | N63: =IF(A63="","",G63*J63) | O63: =IF(A63="","",M63-N63) | AB63: =SUMPRODUCT(--(R63:AA63>0),'Настройки цен'!$B$12:$K$12) -> 0 | AC63: =IF(AB63=0,"",SUMPRODUCT(R63:AA63,'Настройки цен'!$B$11:$K$11,'Настройки цен'!$B$12:$K$12)/AB63) | AE63: =IF(AD63<>"",AD63,IFERROR(IF(INDEX('Настройки цен'!$B$17:$B$24,MATCH(E63,'Настройки цен'!$A$17:$A$24,0))="",'Настройки цен'!$B$5,INDEX('Настройки цен'!$B$17:$B$24,MATCH(E63,'Настройки цен'!$A$17:$A$24,0))),'Настройки цен'!$B$5)) -> 0 | AF63: =IF(AC63="","",ROUND(AC63*(1+AE63)/'Настройки цен'!$B$6,0)*'Настройки цен'!$B$6) | AG63: =IF(OR(AC63="",H63=""),"",H63/AC63-1)
B64: Удлинитель соска колеса | D64: ГАЗ | E64: Другое | H64: 1500 | I64: 17 | K64: =I64-J64 -> 17 | L64: =K64*H64 -> 25500 | M64: =IF(A64="","",H64*J64) | N64: =IF(A64="","",G64*J64) | O64: =IF(A64="","",M64-N64) | AB64: =SUMPRODUCT(--(R64:AA64>0),'Настройки цен'!$B$12:$K$12) -> 0 | AC64: =IF(AB64=0,"",SUMPRODUCT(R64:AA64,'Настройки цен'!$B$11:$K$11,'Настройки цен'!$B$12:$K$12)/AB64) | AE64: =IF(AD64<>"",AD64,IFERROR(IF(INDEX('Настройки цен'!$B$17:$B$24,MATCH(E64,'Настройки цен'!$A$17:$A$24,0))="",'Настройки цен'!$B$5,INDEX('Настройки цен'!$B$17:$B$24,MATCH(E64,'Настройки цен'!$A$17:$A$24,0))),'Настройки цен'!$B$5)) -> 0 | AF64: =IF(AC64="","",ROUND(AC64*(1+AE64)/'Настройки цен'!$B$6,0)*'Настройки цен'!$B$6) | AG64: =IF(OR(AC64="",H64=""),"",H64/AC64-1)
B65: Тормозная трубка | D65: УАЗ/ГАЗ | E65: Тормоза | H65: 3000 | I65: 42 | K65: =I65-J65 -> 42 | L65: =K65*H65 -> 126000 | M65: =IF(A65="","",H65*J65) | N65: =IF(A65="","",G65*J65) | O65: =IF(A65="","",M65-N65) | AB65: =SUMPRODUCT(--(R65:AA65>0),'Настройки цен'!$B$12:$K$12) -> 0 | AC65: =IF(AB65=0,"",SUMPRODUCT(R65:AA65,'Настройки цен'!$B$11:$K$11,'Настройки цен'!$B$12:$K$12)/AB65) | AE65: =IF(AD65<>"",AD65,IFERROR(IF(INDEX('Настройки цен'!$B$17:$B$24,MATCH(E65,'Настройки цен'!$A$17:$A$24,0))="",'Настройки цен'!$B$5,INDEX('Настройки цен'!$B$17:$B$24,MATCH(E65,'Настройки цен'!$A$17:$A$24,0))),'Настройки цен'!$B$5)) -> 0 | AF65: =IF(AC65="","",ROUND(AC65*(1+AE65)/'Настройки цен'!$B$6,0)*'Настройки цен'!$B$6) | AG65: =IF(OR(AC65="",H65=""),"",H65/AC65-1)
B66: Трос спидометра | D66: УАЗ | E66: Электрика | H66: 5000 | I66: 3 | K66: =I66-J66 -> 3 | L66: =K66*H66 -> 15000 | M66: =IF(A66="","",H66*J66) | N66: =IF(A66="","",G66*J66) | O66: =IF(A66="","",M66-N66) | AB66: =SUMPRODUCT(--(R66:AA66>0),'Настройки цен'!$B$12:$K$12) -> 0 | AC66: =IF(AB66=0,"",SUMPRODUCT(R66:AA66,'Настройки цен'!$B$11:$K$11,'Настройки цен'!$B$12:$K$12)/AB66) | AE66: =IF(AD66<>"",AD66,IFERROR(IF(INDEX('Настройки цен'!$B$17:$B$24,MATCH(E66,'Настройки цен'!$A$17:$A$24,0))="",'Настройки цен'!$B$5,INDEX('Настройки цен'!$B$17:$B$24,MATCH(E66,'Настройки цен'!$A$17:$A$24,0))),'Настройки цен'!$B$5)) -> 0 | AF66: =IF(AC66="","",ROUND(AC66*(1+AE66)/'Настройки цен'!$B$6,0)*'Настройки цен'!$B$6) | AG66: =IF(OR(AC66="",H66=""),"",H66/AC66-1)
B67: Трос подсоса | D67: УАЗ | E67: Двигатель | H67: 3000 | I67: 1 | K67: =I67-J67 -> 1 | L67: =K67*H67 -> 3000 | M67: =IF(A67="","",H67*J67) | N67: =IF(A67="","",G67*J67) | O67: =IF(A67="","",M67-N67) | AB67: =SUMPRODUCT(--(R67:AA67>0),'Настройки цен'!$B$12:$K$12) -> 0 | AC67: =IF(AB67=0,"",SUMPRODUCT(R67:AA67,'Настройки цен'!$B$11:$K$11,'Настройки цен'!$B$12:$K$12)/AB67) | AE67: =IF(AD67<>"",AD67,IFERROR(IF(INDEX('Настройки цен'!$B$17:$B$24,MATCH(E67,'Настройки цен'!$A$17:$A$24,0))="",'Настройки цен'!$B$5,INDEX('Настройки цен'!$B$17:$B$24,MATCH(E67,'Настройки цен'!$A$17:$A$24,0))),'Настройки цен'!$B$5)) -> 0 | AF67: =IF(AC67="","",ROUND(AC67*(1+AE67)/'Настройки цен'!$B$6,0)*'Настройки цен'!$B$6) | AG67: =IF(OR(AC67="",H67=""),"",H67/AC67-1)
A68: 45150170105010 | B68: Промвал КПП 4-ст старого образца | D68: УАЗ | E68: Подвеска | H68: 17000 | I68: 4 | K68: =I68-J68 -> 4 | L68: =K68*H68 -> 68000 | M68: =IF(A68="","",H68*J68) -> 0 | N68: =IF(A68="","",G68*J68) -> 0 | O68: =IF(A68="","",M68-N68) -> 0 | Q68: 45150170105010 | AB68: =SUMPRODUCT(--(R68:AA68>0),'Настройки цен'!$B$12:$K$12) -> 0 | AC68: =IF(AB68=0,"",SUMPRODUCT(R68:AA68,'Настройки цен'!$B$11:$K$11,'Настройки цен'!$B$12:$K$12)/AB68) | AE68: =IF(AD68<>"",AD68,IFERROR(IF(INDEX('Настройки цен'!$B$17:$B$24,MATCH(E68,'Настройки цен'!$A$17:$A$24,0))="",'Настройки цен'!$B$5,INDEX('Настройки цен'!$B$17:$B$24,MATCH(E68,'Настройки цен'!$A$17:$A$24,0))),'Настройки цен'!$B$5)) -> 0 | AF68: =IF(AC68="","",ROUND(AC68*(1+AE68)/'Настройки цен'!$B$6,0)*'Настройки цен'!$B$6) | AG68: =IF(OR(AC68="",H68=""),"",H68/AC68-1)
A69: 6900230408000 | B69: Цапфа поворотного кулака | D69: УАЗ | E69: Подвеска | H69: 30000 | I69: 6 | K69: =I69-J69 -> 6 | L69: =K69*H69 -> 180000 | M69: =IF(A69="","",H69*J69) -> 0 | N69: =IF(A69="","",G69*J69) -> 0 | O69: =IF(A69="","",M69-N69) -> 0 | Q69: 6900230408000 | AB69: =SUMPRODUCT(--(R69:AA69>0),'Настройки цен'!$B$12:$K$12) -> 0 | AC69: =IF(AB69=0,"",SUMPRODUCT(R69:AA69,'Настройки цен'!$B$11:$K$11,'Настройки цен'!$B$12:$K$12)/AB69) | AE69: =IF(AD69<>"",AD69,IFERROR(IF(INDEX('Настройки цен'!$B$17:$B$24,MATCH(E69,'Настройки цен'!$A$17:$A$24,0))="",'Настройки цен'!$B$5,INDEX('Настройки цен'!$B$17:$B$24,MATCH(E69,'Настройки цен'!$A$17:$A$24,0))),'Настройки цен'!$B$5)) -> 0 | AF69: =IF(AC69="","",ROUND(AC69*(1+AE69)/'Настройки цен'!$B$6,0)*'Настройки цен'!$B$6) | AG69: =IF(OR(AC69="",H69=""),"",H69/AC69-1)
A70: 46900170104600 | B70: Промвал КПП 4-ст нового образца | D70: УАЗ | E70: Подвеска | H70: 40000 | I70: 4 | K70: =I70-J70 -> 4 | L70: =K70*H70 -> 160000 | M70: =IF(A70="","",H70*J70) -> 0 | N70: =IF(A70="","",G70*J70) -> 0 | O70: =IF(A70="","",M70-N70) -> 0 | Q70: 46900170104600 | AB70: =SUMPRODUCT(--(R70:AA70>0),'Настройки цен'!$B$12:$K$12) -> 0 | AC70: =IF(AB70=0,"",SUMPRODUCT(R70:AA70,'Настройки цен'!$B$11:$K$11,'Настройки цен'!$B$12:$K$12)/AB70) | AE70: =IF(AD70<>"",AD70,IFERROR(IF(INDEX('Настройки цен'!$B$17:$B$24,MATCH(E70,'Настройки цен'!$A$17:$A$24,0))="",'Настройки цен'!$B$5,INDEX('Настройки цен'!$B$17:$B$24,MATCH(E70,'Настройки цен'!$A$17:$A$24,0))),'Настройки цен'!$B$5)) -> 0 | AF70: =IF(AC70="","",ROUND(AC70*(1+AE70)/'Настройки цен'!$B$6,0)*'Настройки цен'!$B$6) | AG70: =IF(OR(AC70="",H70=""),"",H70/AC70-1)
A71: 53121701302 | B71: Первичный вал ГАЗ 53 | D71: ГАЗ | E71: Подвеска | H71: 16000 | I71: 7 | K71: =I71-J71 -> 7 | L71: =K71*H71 -> 112000 | M71: =IF(A71="","",H71*J71) -> 0 | N71: =IF(A71="","",G71*J71) -> 0 | O71: =IF(A71="","",M71-N71) -> 0 | Q71: 53121701302 | AB71: =SUMPRODUCT(--(R71:AA71>0),'Настройки цен'!$B$12:$K$12) -> 0 | AC71: =IF(AB71=0,"",SUMPRODUCT(R71:AA71,'Настройки цен'!$B$11:$K$11,'Настройки цен'!$B$12:$K$12)/AB71) | AE71: =IF(AD71<>"",AD71,IFERROR(IF(INDEX('Настройки цен'!$B$17:$B$24,MATCH(E71,'Настройки цен'!$A$17:$A$24,0))="",'Настройки цен'!$B$5,INDEX('Настройки цен'!$B$17:$B$24,MATCH(E71,'Настройки цен'!$A$17:$A$24,0))),'Настройки цен'!$B$5)) -> 0 | AF71: =IF(AC71="","",ROUND(AC71*(1+AE71)/'Настройки цен'!$B$6,0)*'Настройки цен'!$B$6) | AG71: =IF(OR(AC71="",H71=""),"",H71/AC71-1)
A72: 53А170201002 | B72: Крышка КПП на газ 3307 в сборе | D72: ГАЗ | E72: Подвеска | H72: 65000 | I72: 3 | K72: =I72-J72 -> 3 | L72: =K72*H72 -> 195000 | M72: =IF(A72="","",H72*J72) -> 0 | N72: =IF(A72="","",G72*J72) -> 0 | O72: =IF(A72="","",M72-N72) -> 0 | Q72: 53А170201002 | AB72: =SUMPRODUCT(--(R72:AA72>0),'Настройки цен'!$B$12:$K$12) -> 0 | AC72: =IF(AB72=0,"",SUMPRODUCT(R72:AA72,'Настройки цен'!$B$11:$K$11,'Настройки цен'!$B$12:$K$12)/AB72) | AE72: =IF(AD72<>"",AD72,IFERROR(IF(INDEX('Настройки цен'!$B$17:$B$24,MATCH(E72,'Настройки цен'!$A$17:$A$24,0))="",'Настройки цен'!$B$5,INDEX('Настройки цен'!$B$17:$B$24,MATCH(E72,'Настройки цен'!$A$17:$A$24,0))),'Настройки цен'!$B$5)) -> 0 | AF72: =IF(AC72="","",ROUND(AC72*(1+AE72)/'Настройки цен'!$B$6,0)*'Настройки цен'!$B$6) | AG72: =IF(OR(AC72="",H72=""),"",H72/AC72-1)
B73: Крышка КПП Газ 3307 | D73: ГАЗ | E73: Подвеска | H73: 35000 | I73: 1 | K73: =I73-J73 -> 1 | L73: =K73*H73 -> 35000 | M73: =IF(A73="","",H73*J73) | N73: =IF(A73="","",G73*J73) | O73: =IF(A73="","",M73-N73) | AB73: =SUMPRODUCT(--(R73:AA73>0),'Настройки цен'!$B$12:$K$12) -> 0 | AC73: =IF(AB73=0,"",SUMPRODUCT(R73:AA73,'Настройки цен'!$B$11:$K$11,'Настройки цен'!$B$12:$K$12)/AB73) | AE73: =IF(AD73<>"",AD73,IFERROR(IF(INDEX('Настройки цен'!$B$17:$B$24,MATCH(E73,'Настройки цен'!$A$17:$A$24,0))="",'Настройки цен'!$B$5,INDEX('Настройки цен'!$B$17:$B$24,MATCH(E73,'Настройки цен'!$A$17:$A$24,0))),'Настройки цен'!$B$5)) -> 0 | AF73: =IF(AC73="","",ROUND(AC73*(1+AE73)/'Настройки цен'!$B$6,0)*'Настройки цен'!$B$6) | AG73: =IF(OR(AC73="",H73=""),"",H73/AC73-1)
A74: 451170201510 | B74: Крышка КПП | D74: УАЗ | E74: Подвеска | H74: 25000 | I74: 4 | K74: =I74-J74 -> 4 | L74: =K74*H74 -> 100000 | M74: =IF(A74="","",H74*J74) -> 0 | N74: =IF(A74="","",G74*J74) -> 0 | O74: =IF(A74="","",M74-N74) -> 0 | Q74: 451170201510 | AB74: =SUMPRODUCT(--(R74:AA74>0),'Настройки цен'!$B$12:$K$12) -> 0 | AC74: =IF(AB74=0,"",SUMPRODUCT(R74:AA74,'Настройки цен'!$B$11:$K$11,'Настройки цен'!$B$12:$K$12)/AB74) | AE74: =IF(AD74<>"",AD74,IFERROR(IF(INDEX('Настройки цен'!$B$17:$B$24,MATCH(E74,'Настройки цен'!$A$17:$A$24,0))="",'Настройки цен'!$B$5,INDEX('Настройки цен'!$B$17:$B$24,MATCH(E74,'Настройки цен'!$A$17:$A$24,0))),'Настройки цен'!$B$5)) -> 0 | AF74: =IF(AC74="","",ROUND(AC74*(1+AE74)/'Настройки цен'!$B$6,0)*'Настройки цен'!$B$6) | AG74: =IF(OR(AC74="",H74=""),"",H74/AC74-1)
B75: Блок шестерен КПП | D75: ГАЗ | E75: Подвеска | H75: 50000 | I75: 7 | K75: =I75-J75 -> 7 | L75: =K75*H75 -> 350000 | M75: =IF(A75="","",H75*J75) | N75: =IF(A75="","",G75*J75) | O75: =IF(A75="","",M75-N75) | AB75: =SUMPRODUCT(--(R75:AA75>0),'Настройки цен'!$B$12:$K$12) -> 0 | AC75: =IF(AB75=0,"",SUMPRODUCT(R75:AA75,'Настройки цен'!$B$11:$K$11,'Настройки цен'!$B$12:$K$12)/AB75) | AE75: =IF(AD75<>"",AD75,IFERROR(IF(INDEX('Настройки цен'!$B$17:$B$24,MATCH(E75,'Настройки цен'!$A$17:$A$24,0))="",'Настройки цен'!$B$5,INDEX('Настройки цен'!$B$17:$B$24,MATCH(E75,'Настройки цен'!$A$17:$A$24,0))),'Настройки цен'!$B$5)) -> 0 | AF75: =IF(AC75="","",ROUND(AC75*(1+AE75)/'Настройки цен'!$B$6,0)*'Настройки цен'!$B$6) | AG75: =IF(OR(AC75="",H75=""),"",H75/AC75-1)
A76: 469170201530 | B76: Крышка КПП старого образца | D76: УАЗ | E76: Подвеска | H76: 25000 | I76: 1 | K76: =I76-J76 -> 1 | L76: =K76*H76 -> 25000 | M76: =IF(A76="","",H76*J76) -> 0 | N76: =IF(A76="","",G76*J76) -> 0 | O76: =IF(A76="","",M76-N76) -> 0 | Q76: 469170201530 | AB76: =SUMPRODUCT(--(R76:AA76>0),'Настройки цен'!$B$12:$K$12) -> 0 | AC76: =IF(AB76=0,"",SUMPRODUCT(R76:AA76,'Настройки цен'!$B$11:$K$11,'Настройки цен'!$B$12:$K$12)/AB76) | AE76: =IF(AD76<>"",AD76,IFERROR(IF(INDEX('Настройки цен'!$B$17:$B$24,MATCH(E76,'Настройки цен'!$A$17:$A$24,0))="",'Настройки цен'!$B$5,INDEX('Настройки цен'!$B$17:$B$24,MATCH(E76,'Настройки цен'!$A$17:$A$24,0))),'Настройки цен'!$B$5)) -> 0 | AF76: =IF(AC76="","",ROUND(AC76*(1+AE76)/'Настройки цен'!$B$6,0)*'Настройки цен'!$B$6) | AG76: =IF(OR(AC76="",H76=""),"",H76/AC76-1)
A77: 45150290244592 | B77: Кронштейн рессоры | D77: УАЗ | E77: Подвеска | H77: 15000 | I77: 4 | K77: =I77-J77 -> 4 | L77: =K77*H77 -> 60000 | M77: =IF(A77="","",H77*J77) -> 0 | N77: =IF(A77="","",G77*J77) -> 0 | O77: =IF(A77="","",M77-N77) -> 0 | Q77: 45150290244592 | AB77: =SUMPRODUCT(--(R77:AA77>0),'Настройки цен'!$B$12:$K$12) -> 0 | AC77: =IF(AB77=0,"",SUMPRODUCT(R77:AA77,'Настройки цен'!$B$11:$K$11,'Настройки цен'!$B$12:$K$12)/AB77) | AE77: =IF(AD77<>"",AD77,IFERROR(IF(INDEX('Настройки цен'!$B$17:$B$24,MATCH(E77,'Настройки цен'!$A$17:$A$24,0))="",'Настройки цен'!$B$5,INDEX('Настройки цен'!$B$17:$B$24,MATCH(E77,'Настройки цен'!$A$17:$A$24,0))),'Настройки цен'!$B$5)) -> 0 | AF77: =IF(AC77="","",ROUND(AC77*(1+AE77)/'Настройки цен'!$B$6,0)*'Настройки цен'!$B$6) | AG77: =IF(OR(AC77="",H77=""),"",H77/AC77-1)
A78: 451Д1701030 | B78: Первичный вал КПП | D78: УАЗ | E78: Подвеска | H78: 17000 | I78: 3 | K78: =I78-J78 -> 3 | L78: =K78*H78 -> 51000 | M78: =IF(A78="","",H78*J78) -> 0 | N78: =IF(A78="","",G78*J78) -> 0 | O78: =IF(A78="","",M78-N78) -> 0 | Q78: 451Д1701030 | AB78: =SUMPRODUCT(--(R78:AA78>0),'Настройки цен'!$B$12:$K$12) -> 0 | AC78: =IF(AB78=0,"",SUMPRODUCT(R78:AA78,'Настройки цен'!$B$11:$K$11,'Настройки цен'!$B$12:$K$12)/AB78) | AE78: =IF(AD78<>"",AD78,IFERROR(IF(INDEX('Настройки цен'!$B$17:$B$24,MATCH(E78,'Настройки цен'!$A$17:$A$24,0))="",'Настройки цен'!$B$5,INDEX('Настройки цен'!$B$17:$B$24,MATCH(E78,'Настройки цен'!$A$17:$A$24,0))),'Настройки цен'!$B$5)) -> 0 | AF78: =IF(AC78="","",ROUND(AC78*(1+AE78)/'Настройки цен'!$B$6,0)*'Настройки цен'!$B$6) | AG78: =IF(OR(AC78="",H78=""),"",H78/AC78-1)
A79: 69180207501 | B79: Фланец вала привода заднего моста | D79: УАЗ | E79: Подвеска | H79: 7000 | I79: 6 | K79: =I79-J79 -> 6 | L79: =K79*H79 -> 42000 | M79: =IF(A79="","",H79*J79) -> 0 | N79: =IF(A79="","",G79*J79) -> 0 | O79: =IF(A79="","",M79-N79) -> 0 | Q79: 69180207501 | AB79: =SUMPRODUCT(--(R79:AA79>0),'Настройки цен'!$B$12:$K$12) -> 0 | AC79: =IF(AB79=0,"",SUMPRODUCT(R79:AA79,'Настройки цен'!$B$11:$K$11,'Настройки цен'!$B$12:$K$12)/AB79) | AE79: =IF(AD79<>"",AD79,IFERROR(IF(INDEX('Настройки цен'!$B$17:$B$24,MATCH(E79,'Настройки цен'!$A$17:$A$24,0))="",'Настройки цен'!$B$5,INDEX('Настройки цен'!$B$17:$B$24,MATCH(E79,'Настройки цен'!$A$17:$A$24,0))),'Настройки цен'!$B$5)) -> 0 | AF79: =IF(AC79="","",ROUND(AC79*(1+AE79)/'Настройки цен'!$B$6,0)*'Настройки цен'!$B$6) | AG79: =IF(OR(AC79="",H79=""),"",H79/AC79-1)
A80: 69310301501 | B80: Ступица колеса | D80: УАЗ/ГАЗ | E80: Подвеска | H80: 17000 | I80: 4 | K80: =I80-J80 -> 4 | L80: =K80*H80 -> 68000 | M80: =IF(A80="","",H80*J80) -> 0 | N80: =IF(A80="","",G80*J80) -> 0 | O80: =IF(A80="","",M80-N80) -> 0 | Q80: 69310301501 | AB80: =SUMPRODUCT(--(R80:AA80>0),'Настройки цен'!$B$12:$K$12) -> 0 | AC80: =IF(AB80=0,"",SUMPRODUCT(R80:AA80,'Настройки цен'!$B$11:$K$11,'Настройки цен'!$B$12:$K$12)/AB80) | AE80: =IF(AD80<>"",AD80,IFERROR(IF(INDEX('Настройки цен'!$B$17:$B$24,MATCH(E80,'Настройки цен'!$A$17:$A$24,0))="",'Настройки цен'!$B$5,INDEX('Настройки цен'!$B$17:$B$24,MATCH(E80,'Настройки цен'!$A$17:$A$24,0))),'Настройки цен'!$B$5)) -> 0 | AF80: =IF(AC80="","",ROUND(AC80*(1+AE80)/'Настройки цен'!$B$6,0)*'Настройки цен'!$B$6) | AG80: =IF(OR(AC80="",H80=""),"",H80/AC80-1)
A81: 452170101522 | B81: Корпус КПП старого образца | D81: УАЗ | E81: Подвеска | H81: 65000 | I81: 2 | K81: =I81-J81 -> 2 | L81: =K81*H81 -> 130000 | M81: =IF(A81="","",H81*J81) -> 0 | N81: =IF(A81="","",G81*J81) -> 0 | O81: =IF(A81="","",M81-N81) -> 0 | Q81: 452170101522 | AB81: =SUMPRODUCT(--(R81:AA81>0),'Настройки цен'!$B$12:$K$12) -> 0 | AC81: =IF(AB81=0,"",SUMPRODUCT(R81:AA81,'Настройки цен'!$B$11:$K$11,'Настройки цен'!$B$12:$K$12)/AB81) | AE81: =IF(AD81<>"",AD81,IFERROR(IF(INDEX('Настройки цен'!$B$17:$B$24,MATCH(E81,'Настройки цен'!$A$17:$A$24,0))="",'Настройки цен'!$B$5,INDEX('Настройки цен'!$B$17:$B$24,MATCH(E81,'Настройки цен'!$A$17:$A$24,0))),'Настройки цен'!$B$5)) -> 0 | AF81: =IF(AC81="","",ROUND(AC81*(1+AE81)/'Настройки цен'!$B$6,0)*'Настройки цен'!$B$6) | AG81: =IF(OR(AC81="",H81=""),"",H81/AC81-1)
A82: 521701080 | B82: Блок шестерен заднего хода | D82: ГАЗ | E82: Подвеска | H82: 17000 | I82: 7 | K82: =I82-J82 -> 7 | L82: =K82*H82 -> 119000 | M82: =IF(A82="","",H82*J82) -> 0 | N82: =IF(A82="","",G82*J82) -> 0 | O82: =IF(A82="","",M82-N82) -> 0 | Q82: 521701080 | AB82: =SUMPRODUCT(--(R82:AA82>0),'Настройки цен'!$B$12:$K$12) -> 0 | AC82: =IF(AB82=0,"",SUMPRODUCT(R82:AA82,'Настройки цен'!$B$11:$K$11,'Настройки цен'!$B$12:$K$12)/AB82) | AE82: =IF(AD82<>"",AD82,IFERROR(IF(INDEX('Настройки цен'!$B$17:$B$24,MATCH(E82,'Настройки цен'!$A$17:$A$24,0))="",'Настройки цен'!$B$5,INDEX('Настройки цен'!$B$17:$B$24,MATCH(E82,'Настройки цен'!$A$17:$A$24,0))),'Настройки цен'!$B$5)) -> 0 | AF82: =IF(AC82="","",ROUND(AC82*(1+AE82)/'Настройки цен'!$B$6,0)*'Настройки цен'!$B$6) | AG82: =IF(OR(AC82="",H82=""),"",H82/AC82-1)
A83: 521701111 | B83: Шестерня второй передачи | D83: ГАЗ | E83: Подвеска | H83: 20000 | I83: 2 | K83: =I83-J83 -> 2 | L83: =K83*H83 -> 40000 | M83: =IF(A83="","",H83*J83) -> 0 | N83: =IF(A83="","",G83*J83) -> 0 | O83: =IF(A83="","",M83-N83) -> 0 | Q83: 521701111 | AB83: =SUMPRODUCT(--(R83:AA83>0),'Настройки цен'!$B$12:$K$12) -> 0 | AC83: =IF(AB83=0,"",SUMPRODUCT(R83:AA83,'Настройки цен'!$B$11:$K$11,'Настройки цен'!$B$12:$K$12)/AB83) | AE83: =IF(AD83<>"",AD83,IFERROR(IF(INDEX('Настройки цен'!$B$17:$B$24,MATCH(E83,'Настройки цен'!$A$17:$A$24,0))="",'Настройки цен'!$B$5,INDEX('Настройки цен'!$B$17:$B$24,MATCH(E83,'Настройки цен'!$A$17:$A$24,0))),'Настройки цен'!$B$5)) -> 0 | AF83: =IF(AC83="","",ROUND(AC83*(1+AE83)/'Настройки цен'!$B$6,0)*'Настройки цен'!$B$6) | AG83: =IF(OR(AC83="",H83=""),"",H83/AC83-1)
A84: 52170111031 | B84: Шестерня первой передачи | D84: ГАЗ | E84: Подвеска | H84: 20000 | I84: 3 | K84: =I84-J84 -> 3 | L84: =K84*H84 -> 60000 | M84: =IF(A84="","",H84*J84) -> 0 | N84: =IF(A84="","",G84*J84) -> 0 | O84: =IF(A84="","",M84-N84) -> 0 | Q84: 52170111031 | AB84: =SUMPRODUCT(--(R84:AA84>0),'Настройки цен'!$B$12:$K$12) -> 0 | AC84: =IF(AB84=0,"",SUMPRODUCT(R84:AA84,'Настройки цен'!$B$11:$K$11,'Настройки цен'!$B$12:$K$12)/AB84) | AE84: =IF(AD84<>"",AD84,IFERROR(IF(INDEX('Настройки цен'!$B$17:$B$24,MATCH(E84,'Настройки цен'!$A$17:$A$24,0))="",'Настройки цен'!$B$5,INDEX('Настройки цен'!$B$17:$B$24,MATCH(E84,'Настройки цен'!$A$17:$A$24,0))),'Настройки цен'!$B$5)) -> 0 | AF84: =IF(AC84="","",ROUND(AC84*(1+AE84)/'Настройки цен'!$B$6,0)*'Настройки цен'!$B$6) | AG84: =IF(OR(AC84="",H84=""),"",H84/AC84-1)
A85: 631802076 | B85: Фланец первичного вала РК | D85: ГАЗ | E85: Подвеска | H85: 20000 | I85: 6 | K85: =I85-J85 -> 6 | L85: =K85*H85 -> 120000 | M85: =IF(A85="","",H85*J85) -> 0 | N85: =IF(A85="","",G85*J85) -> 0 | O85: =IF(A85="","",M85-N85) -> 0 | Q85: 631802076 | AB85: =SUMPRODUCT(--(R85:AA85>0),'Настройки цен'!$B$12:$K$12) -> 0 | AC85: =IF(AB85=0,"",SUMPRODUCT(R85:AA85,'Настройки цен'!$B$11:$K$11,'Настройки цен'!$B$12:$K$12)/AB85) | AE85: =IF(AD85<>"",AD85,IFERROR(IF(INDEX('Настройки цен'!$B$17:$B$24,MATCH(E85,'Настройки цен'!$A$17:$A$24,0))="",'Настройки цен'!$B$5,INDEX('Настройки цен'!$B$17:$B$24,MATCH(E85,'Настройки цен'!$A$17:$A$24,0))),'Настройки цен'!$B$5)) -> 0 | AF85: =IF(AC85="","",ROUND(AC85*(1+AE85)/'Настройки цен'!$B$6,0)*'Настройки цен'!$B$6) | AG85: =IF(OR(AC85="",H85=""),"",H85/AC85-1)
A86: 6305n | B86: Подшипник пром вала КПП | D86: УАЗ | E86: Подвеска | H86: 5000 | I86: 1 | K86: =I86-J86 -> 1 | L86: =K86*H86 -> 5000 | M86: =IF(A86="","",H86*J86) -> 0 | N86: =IF(A86="","",G86*J86) -> 0 | O86: =IF(A86="","",M86-N86) -> 0 | Q86: 6305n | AB86: =SUMPRODUCT(--(R86:AA86>0),'Настройки цен'!$B$12:$K$12) -> 0 | AC86: =IF(AB86=0,"",SUMPRODUCT(R86:AA86,'Настройки цен'!$B$11:$K$11,'Настройки цен'!$B$12:$K$12)/AB86) | AE86: =IF(AD86<>"",AD86,IFERROR(IF(INDEX('Настройки цен'!$B$17:$B$24,MATCH(E86,'Настройки цен'!$A$17:$A$24,0))="",'Настройки цен'!$B$5,INDEX('Настройки цен'!$B$17:$B$24,MATCH(E86,'Настройки цен'!$A$17:$A$24,0))),'Настройки цен'!$B$5)) -> 0 | AF86: =IF(AC86="","",ROUND(AC86*(1+AE86)/'Настройки цен'!$B$6,0)*'Настройки цен'!$B$6) | AG86: =IF(OR(AC86="",H86=""),"",H86/AC86-1)
A87: 31513502040 | B87: Задний тормозной цилиндр 25мм | D87: УАЗ | E87: Тормоза | H87: 8000 | I87: 15 | K87: =I87-J87 -> 15 | L87: =K87*H87 -> 120000 | M87: =IF(A87="","",H87*J87) -> 0 | N87: =IF(A87="","",G87*J87) -> 0 | O87: =IF(A87="","",M87-N87) -> 0 | Q87: 31513502040 | AB87: =SUMPRODUCT(--(R87:AA87>0),'Настройки цен'!$B$12:$K$12) -> 0 | AC87: =IF(AB87=0,"",SUMPRODUCT(R87:AA87,'Настройки цен'!$B$11:$K$11,'Настройки цен'!$B$12:$K$12)/AB87) | AE87: =IF(AD87<>"",AD87,IFERROR(IF(INDEX('Настройки цен'!$B$17:$B$24,MATCH(E87,'Настройки цен'!$A$17:$A$24,0))="",'Настройки цен'!$B$5,INDEX('Настройки цен'!$B$17:$B$24,MATCH(E87,'Настройки цен'!$A$17:$A$24,0))),'Настройки цен'!$B$5)) -> 0 | AF87: =IF(AC87="","",ROUND(AC87*(1+AE87)/'Настройки цен'!$B$6,0)*'Настройки цен'!$B$6) | AG87: =IF(OR(AC87="",H87=""),"",H87/AC87-1)
A88: 4693502040 | B88: Задний тормозной цилиндр 32мм | D88: УАЗ | E88: Тормоза | H88: 8000 | I88: 9 | K88: =I88-J88 -> 9 | L88: =K88*H88 -> 72000 | M88: =IF(A88="","",H88*J88) -> 0 | N88: =IF(A88="","",G88*J88) -> 0 | O88: =IF(A88="","",M88-N88) -> 0 | Q88: 4693502040 | AB88: =SUMPRODUCT(--(R88:AA88>0),'Настройки цен'!$B$12:$K$12) -> 0 | AC88: =IF(AB88=0,"",SUMPRODUCT(R88:AA88,'Настройки цен'!$B$11:$K$11,'Настройки цен'!$B$12:$K$12)/AB88) | AE88: =IF(AD88<>"",AD88,IFERROR(IF(INDEX('Настройки цен'!$B$17:$B$24,MATCH(E88,'Настройки цен'!$A$17:$A$24,0))="",'Настройки цен'!$B$5,INDEX('Настройки цен'!$B$17:$B$24,MATCH(E88,'Настройки цен'!$A$17:$A$24,0))),'Настройки цен'!$B$5)) -> 0 | AF88: =IF(AC88="","",ROUND(AC88*(1+AE88)/'Настройки цен'!$B$6,0)*'Настройки цен'!$B$6) | AG88: =IF(OR(AC88="",H88=""),"",H88/AC88-1)
A89: 521701020 | B89: Крышка люка вала отбора мощности или КПП | D89: ГАЗ | E89: Подвеска | H89: 3000 | I89: 8 | K89: =I89-J89 -> 8 | L89: =K89*H89 -> 24000 | M89: =IF(A89="","",H89*J89) -> 0 | N89: =IF(A89="","",G89*J89) -> 0 | O89: =IF(A89="","",M89-N89) -> 0 | Q89: 521701020 | AB89: =SUMPRODUCT(--(R89:AA89>0),'Настройки цен'!$B$12:$K$12) -> 0 | AC89: =IF(AB89=0,"",SUMPRODUCT(R89:AA89,'Настройки цен'!$B$11:$K$11,'Настройки цен'!$B$12:$K$12)/AB89) | AE89: =IF(AD89<>"",AD89,IFERROR(IF(INDEX('Настройки цен'!$B$17:$B$24,MATCH(E89,'Настройки цен'!$A$17:$A$24,0))="",'Настройки цен'!$B$5,INDEX('Настройки цен'!$B$17:$B$24,MATCH(E89,'Настройки цен'!$A$17:$A$24,0))),'Настройки цен'!$B$5)) -> 0 | AF89: =IF(AC89="","",ROUND(AC89*(1+AE89)/'Настройки цен'!$B$6,0)*'Настройки цен'!$B$6) | AG89: =IF(OR(AC89="",H89=""),"",H89/AC89-1)
A90: 53121701101 | B90: Вторичный вал КПП | D90: ГАЗ | E90: Подвеска | H90: 25000 | I90: 6 | K90: =I90-J90 -> 6 | L90: =K90*H90 -> 150000 | M90: =IF(A90="","",H90*J90) -> 0 | N90: =IF(A90="","",G90*J90) -> 0 | O90: =IF(A90="","",M90-N90) -> 0 | Q90: 53121701101 | AB90: =SUMPRODUCT(--(R90:AA90>0),'Настройки цен'!$B$12:$K$12) -> 0 | AC90: =IF(AB90=0,"",SUMPRODUCT(R90:AA90,'Настройки цен'!$B$11:$K$11,'Настройки цен'!$B$12:$K$12)/AB90) | AE90: =IF(AD90<>"",AD90,IFERROR(IF(INDEX('Настройки цен'!$B$17:$B$24,MATCH(E90,'Настройки цен'!$A$17:$A$24,0))="",'Настройки цен'!$B$5,INDEX('Настройки цен'!$B$17:$B$24,MATCH(E90,'Настройки цен'!$A$17:$A$24,0))),'Настройки цен'!$B$5)) -> 0 | AF90: =IF(AC90="","",ROUND(AC90*(1+AE90)/'Настройки цен'!$B$6,0)*'Настройки цен'!$B$6) | AG90: =IF(OR(AC90="",H90=""),"",H90/AC90-1)
A91: 4521700010 | B91: КПП 4-ст старого образца | D91: Уаз | E91: Подвеска | H91: 300000 | I91: 1 | K91: =I91-J91 -> 1 | L91: =K91*H91 -> 300000 | M91: =IF(A91="","",H91*J91) -> 0 | N91: =IF(A91="","",G91*J91) -> 0 | O91: =IF(A91="","",M91-N91) -> 0 | Q91: 4521700010 | AB91: =SUMPRODUCT(--(R91:AA91>0),'Настройки цен'!$B$12:$K$12) -> 0 | AC91: =IF(AB91=0,"",SUMPRODUCT(R91:AA91,'Настройки цен'!$B$11:$K$11,'Настройки цен'!$B$12:$K$12)/AB91) | AE91: =IF(AD91<>"",AD91,IFERROR(IF(INDEX('Настройки цен'!$B$17:$B$24,MATCH(E91,'Настройки цен'!$A$17:$A$24,0))="",'Настройки цен'!$B$5,INDEX('Настройки цен'!$B$17:$B$24,MATCH(E91,'Настройки цен'!$A$17:$A$24,0))),'Настройки цен'!$B$5)) -> 0 | AF91: =IF(AC91="","",ROUND(AC91*(1+AE91)/'Настройки цен'!$B$6,0)*'Настройки цен'!$B$6) | AG91: =IF(OR(AC91="",H91=""),"",H91/AC91-1)
A92: 316200180211000 | B92: Вал привода переднего моста выходной вал раздатки | D92: УАЗ | E92: Подвеска | H92: 25000 | I92: 2 | K92: =I92-J92 -> 2 | L92: =K92*H92 -> 50000 | M92: =IF(A92="","",H92*J92) -> 0 | N92: =IF(A92="","",G92*J92) -> 0 | O92: =IF(A92="","",M92-N92) -> 0 | Q92: 316200180211000 | AB92: =SUMPRODUCT(--(R92:AA92>0),'Настройки цен'!$B$12:$K$12) -> 0 | AC92: =IF(AB92=0,"",SUMPRODUCT(R92:AA92,'Настройки цен'!$B$11:$K$11,'Настройки цен'!$B$12:$K$12)/AB92) | AE92: =IF(AD92<>"",AD92,IFERROR(IF(INDEX('Настройки цен'!$B$17:$B$24,MATCH(E92,'Настройки цен'!$A$17:$A$24,0))="",'Настройки цен'!$B$5,INDEX('Настройки цен'!$B$17:$B$24,MATCH(E92,'Настройки цен'!$A$17:$A$24,0))),'Настройки цен'!$B$5)) -> 0 | AF92: =IF(AC92="","",ROUND(AC92*(1+AE92)/'Настройки цен'!$B$6,0)*'Настройки цен'!$B$6) | AG92: =IF(OR(AC92="",H92=""),"",H92/AC92-1)
A93: 4171005185 | B93: Шестерня коленвала | D93: УАЗ/ГАЗ | E93: Двигатель | H93: 12000 | I93: 1 | K93: =I93-J93 -> 1 | L93: =K93*H93 -> 12000 | M93: =IF(A93="","",H93*J93) -> 0 | N93: =IF(A93="","",G93*J93) -> 0 | O93: =IF(A93="","",M93-N93) -> 0 | Q93: 4171005185 | AB93: =SUMPRODUCT(--(R93:AA93>0),'Настройки цен'!$B$12:$K$12) -> 0 | AC93: =IF(AB93=0,"",SUMPRODUCT(R93:AA93,'Настройки цен'!$B$11:$K$11,'Настройки цен'!$B$12:$K$12)/AB93) | AE93: =IF(AD93<>"",AD93,IFERROR(IF(INDEX('Настройки цен'!$B$17:$B$24,MATCH(E93,'Настройки цен'!$A$17:$A$24,0))="",'Настройки цен'!$B$5,INDEX('Настройки цен'!$B$17:$B$24,MATCH(E93,'Настройки цен'!$A$17:$A$24,0))),'Настройки цен'!$B$5)) -> 0 | AF93: =IF(AC93="","",ROUND(AC93*(1+AE93)/'Настройки цен'!$B$6,0)*'Настройки цен'!$B$6) | AG93: =IF(OR(AC93="",H93=""),"",H93/AC93-1)
A94: 1301005030 | B94: Шестерня коленвала | D94: ЗИЛ | E94: Двигатель | H94: 12000 | I94: 2 | K94: =I94-J94 -> 2 | L94: =K94*H94 -> 24000 | M94: =IF(A94="","",H94*J94) -> 0 | N94: =IF(A94="","",G94*J94) -> 0 | O94: =IF(A94="","",M94-N94) -> 0 | Q94: 1301005030 | AB94: =SUMPRODUCT(--(R94:AA94>0),'Настройки цен'!$B$12:$K$12) -> 0 | AC94: =IF(AB94=0,"",SUMPRODUCT(R94:AA94,'Настройки цен'!$B$11:$K$11,'Настройки цен'!$B$12:$K$12)/AB94) | AE94: =IF(AD94<>"",AD94,IFERROR(IF(INDEX('Настройки цен'!$B$17:$B$24,MATCH(E94,'Настройки цен'!$A$17:$A$24,0))="",'Настройки цен'!$B$5,INDEX('Настройки цен'!$B$17:$B$24,MATCH(E94,'Настройки цен'!$A$17:$A$24,0))),'Настройки цен'!$B$5)) -> 0 | AF94: =IF(AC94="","",ROUND(AC94*(1+AE94)/'Настройки цен'!$B$6,0)*'Настройки цен'!$B$6) | AG94: =IF(OR(AC94="",H94=""),"",H94/AC94-1)
A95: 396295170301000 | B95: Кулиса КПП | D95: УАЗ | E95: Подвеска | H95: 25000 | I95: 1 | K95: =I95-J95 -> 1 | L95: =K95*H95 -> 25000 | M95: =IF(A95="","",H95*J95) -> 0 | N95: =IF(A95="","",G95*J95) -> 0 | O95: =IF(A95="","",M95-N95) -> 0 | Q95: 396295170301000 | AB95: =SUMPRODUCT(--(R95:AA95>0),'Настройки цен'!$B$12:$K$12) -> 0 | AC95: =IF(AB95=0,"",SUMPRODUCT(R95:AA95,'Настройки цен'!$B$11:$K$11,'Настройки цен'!$B$12:$K$12)/AB95) | AE95: =IF(AD95<>"",AD95,IFERROR(IF(INDEX('Настройки цен'!$B$17:$B$24,MATCH(E95,'Настройки цен'!$A$17:$A$24,0))="",'Настройки цен'!$B$5,INDEX('Настройки цен'!$B$17:$B$24,MATCH(E95,'Настройки цен'!$A$17:$A$24,0))),'Настройки цен'!$B$5)) -> 0 | AF95: =IF(AC95="","",ROUND(AC95*(1+AE95)/'Настройки цен'!$B$6,0)*'Настройки цен'!$B$6) | AG95: =IF(OR(AC95="",H95=""),"",H95/AC95-1)
A96: 4211308100 | B96: Привод вентилятора | D96: УАЗ/ГАЗ | E96: Двигатель | H96: 15000 | I96: 2 | K96: =I96-J96 -> 2 | L96: =K96*H96 -> 30000 | M96: =IF(A96="","",H96*J96) -> 0 | N96: =IF(A96="","",G96*J96) -> 0 | O96: =IF(A96="","",M96-N96) -> 0 | Q96: 4211308100 | AB96: =SUMPRODUCT(--(R96:AA96>0),'Настройки цен'!$B$12:$K$12) -> 0 | AC96: =IF(AB96=0,"",SUMPRODUCT(R96:AA96,'Настройки цен'!$B$11:$K$11,'Настройки цен'!$B$12:$K$12)/AB96) | AE96: =IF(AD96<>"",AD96,IFERROR(IF(INDEX('Настройки цен'!$B$17:$B$24,MATCH(E96,'Настройки цен'!$A$17:$A$24,0))="",'Настройки цен'!$B$5,INDEX('Настройки цен'!$B$17:$B$24,MATCH(E96,'Настройки цен'!$A$17:$A$24,0))),'Настройки цен'!$B$5)) -> 0 | AF96: =IF(AC96="","",ROUND(AC96*(1+AE96)/'Настройки цен'!$B$6,0)*'Настройки цен'!$B$6) | AG96: =IF(OR(AC96="",H96=""),"",H96/AC96-1)
A97: 95х130х12х17.5 | B97: Сальник ступицы | D97: ГАЗ | E97: Подвеска | H97: 10000 | I97: 2 | K97: =I97-J97 -> 2 | L97: =K97*H97 -> 20000 | M97: =IF(A97="","",H97*J97) -> 0 | N97: =IF(A97="","",G97*J97) -> 0 | O97: =IF(A97="","",M97-N97) -> 0 | Q97: 95х130х12х17.5 | AB97: =SUMPRODUCT(--(R97:AA97>0),'Настройки цен'!$B$12:$K$12) -> 0 | AC97: =IF(AB97=0,"",SUMPRODUCT(R97:AA97,'Настройки цен'!$B$11:$K$11,'Настройки цен'!$B$12:$K$12)/AB97) | AE97: =IF(AD97<>"",AD97,IFERROR(IF(INDEX('Настройки цен'!$B$17:$B$24,MATCH(E97,'Настройки цен'!$A$17:$A$24,0))="",'Настройки цен'!$B$5,INDEX('Настройки цен'!$B$17:$B$24,MATCH(E97,'Настройки цен'!$A$17:$A$24,0))),'Настройки цен'!$B$5)) -> 0 | AF97: =IF(AC97="","",ROUND(AC97*(1+AE97)/'Настройки цен'!$B$6,0)*'Настройки цен'!$B$6) | AG97: =IF(OR(AC97="",H97=""),"",H97/AC97-1)
A98: 55x80x10 | B98: Сальник коленвала | D98: УАЗ/ГАЗ | E98: Двигатель | H98: 4000 | I98: 5 | K98: =I98-J98 -> 5 | L98: =K98*H98 -> 20000 | M98: =IF(A98="","",H98*J98) -> 0 | N98: =IF(A98="","",G98*J98) -> 0 | O98: =IF(A98="","",M98-N98) -> 0 | Q98: 55x80x10 | AB98: =SUMPRODUCT(--(R98:AA98>0),'Настройки цен'!$B$12:$K$12) -> 0 | AC98: =IF(AB98=0,"",SUMPRODUCT(R98:AA98,'Настройки цен'!$B$11:$K$11,'Настройки цен'!$B$12:$K$12)/AB98) | AE98: =IF(AD98<>"",AD98,IFERROR(IF(INDEX('Настройки цен'!$B$17:$B$24,MATCH(E98,'Настройки цен'!$A$17:$A$24,0))="",'Настройки цен'!$B$5,INDEX('Настройки цен'!$B$17:$B$24,MATCH(E98,'Настройки цен'!$A$17:$A$24,0))),'Настройки цен'!$B$5)) -> 0 | AF98: =IF(AC98="","",ROUND(AC98*(1+AE98)/'Настройки цен'!$B$6,0)*'Настройки цен'!$B$6) | AG98: =IF(OR(AC98="",H98=""),"",H98/AC98-1)
A99: 45x65x10 | B99: Сальник шарнира поворотного кулака | D99: ГАЗ | E99: Подвеска | H99: 2000 | I99: 10 | K99: =I99-J99 -> 10 | L99: =K99*H99 -> 20000 | M99: =IF(A99="","",H99*J99) -> 0 | N99: =IF(A99="","",G99*J99) -> 0 | O99: =IF(A99="","",M99-N99) -> 0 | Q99: 45x65x10 | AB99: =SUMPRODUCT(--(R99:AA99>0),'Настройки цен'!$B$12:$K$12) -> 0 | AC99: =IF(AB99=0,"",SUMPRODUCT(R99:AA99,'Настройки цен'!$B$11:$K$11,'Настройки цен'!$B$12:$K$12)/AB99) | AE99: =IF(AD99<>"",AD99,IFERROR(IF(INDEX('Настройки цен'!$B$17:$B$24,MATCH(E99,'Настройки цен'!$A$17:$A$24,0))="",'Настройки цен'!$B$5,INDEX('Настройки цен'!$B$17:$B$24,MATCH(E99,'Настройки цен'!$A$17:$A$24,0))),'Настройки цен'!$B$5)) -> 0 | AF99: =IF(AC99="","",ROUND(AC99*(1+AE99)/'Настройки цен'!$B$6,0)*'Настройки цен'!$B$6) | AG99: =IF(OR(AC99="",H99=""),"",H99/AC99-1)
A100: 42x75x10 | B100: Сальник редуктора заднего моста | D100: Газель | E100: Подвеска | H100: 2000 | I100: 10 | K100: =I100-J100 -> 10 | L100: =K100*H100 -> 20000 | M100: =IF(A100="","",H100*J100) -> 0 | N100: =IF(A100="","",G100*J100) -> 0 | O100: =IF(A100="","",M100-N100) -> 0 | Q100: 42x75x10 | AB100: =SUMPRODUCT(--(R100:AA100>0),'Настройки цен'!$B$12:$K$12) -> 0 | AC100: =IF(AB100=0,"",SUMPRODUCT(R100:AA100,'Настройки цен'!$B$11:$K$11,'Настройки цен'!$B$12:$K$12)/AB100) | AE100: =IF(AD100<>"",AD100,IFERROR(IF(INDEX('Настройки цен'!$B$17:$B$24,MATCH(E100,'Настройки цен'!$A$17:$A$24,0))="",'Настройки цен'!$B$5,INDEX('Настройки цен'!$B$17:$B$24,MATCH(E100,'Настройки цен'!$A$17:$A$24,0))),'Настройки цен'!$B$5)) -> 0 | AF100: =IF(AC100="","",ROUND(AC100*(1+AE100)/'Настройки цен'!$B$6,0)*'Настройки цен'!$B$6) | AG100: =IF(OR(AC100="",H100=""),"",H100/AC100-1)
...

Sheet Настройки цен
A1: НАСТРОЙКИ ЦЕНООБРАЗОВАНИЯ
A3: Курс рубля, ₸ за 1 ₽ | B3: 5.3
A4: Надбавка к российским ценам (доставка, растаможка), % | B4: 0
A5: Общая наценка на среднюю цену рынка, % | B5: 0
A6: Округлять цену до, ₸ | B6: 100
A9: Источник | B9: autogur73.ru | C9: chipdip.kz | D9: uaz.store | E9: metalpart.ru | F9: detaliuaz.ru | G9: vta-gaz.ru | H9: spectuninguaz.ru | I9: 4uaz.ru | J9: Kaspi | K9: Ozon
A10: Валюта (RUB / KZT) | B10: RUB | C10: KZT | D10: RUB | E10: RUB | F10: RUB | G10: RUB | H10: RUB | I10: RUB | J10: KZT | K10: KZT
A11: Курс пересчёта в ₸ (авто) | B11: =IF(B10="RUB",$B$3*(1+$B$4),1) -> 5.3 | C11: =IF(C10="RUB",$B$3*(1+$B$4),1) -> 1 | D11: =IF(D10="RUB",$B$3*(1+$B$4),1) -> 5.3 | E11: =IF(E10="RUB",$B$3*(1+$B$4),1) -> 5.3 | F11: =IF(F10="RUB",$B$3*(1+$B$4),1) -> 5.3 | G11: =IF(G10="RUB",$B$3*(1+$B$4),1) -> 5.3 | H11: =IF(H10="RUB",$B$3*(1+$B$4),1) -> 5.3 | I11: =IF(I10="RUB",$B$3*(1+$B$4),1) -> 5.3 | ... K11: =IF(K10="RUB",$B$3*(1+$B$4),1) -> 1
A12: Учитывать в средней (1 — да, 0 — нет) | B12: 1 | C12: 1 | D12: 1 | E12: 1 | F12: 1 | G12: 1 | H12: 1 | I12: 1 | J12: 1 | K12: 1
A15: Наценка по категориям (пусто = общая)
A16: Категория | B16: Наценка, %
A17: Двигатель
A18: Другое
A19: Кузов
A20: Подвеска
A21: Расходники
A22: Тормоза
A23: Фильтры
A24: Электрика
A26: Жёлтые ячейки — для изменения. Синий шрифт — вводимые значения, чёрный — формулы.

Sheet Сводка
A1: СВОДКА ПО СКЛАДУ И ПРОДАЖАМ
A2: Показатель | B2: Значение
A3: Всего позиций | B3: =COUNTIF(Запчасти!B2:B501,"<>") -> 278
A4: Всего единиц на остатке | B4: =SUM(Запчасти!K2:K501) -> 2846
A5: Всего товаров на сумму | B5: =Запчасти!L502 -> 13926450 | C5: =B5/450 -> 30947.667 | D5: Это в Долларах
A6: Выручка | B6: =SUM(Запчасти!M2:M501) -> 0
A7: Себестоимость проданного | B7: =SUM(Запчасти!N2:N501) -> 0
A8: Прибыль | B8: =SUM(Запчасти!O2:O501) -> 0

Sheet Как пользоваться
A1: КРАТКАЯ ИНСТРУКЦИЯ | B1: Вносите каждую запчасть отдельной строкой на вкладке «Запчасти».
A2: 2 | B2: Заполняйте артикул, название, производителя, автомобиль, цены и количество.
A3: 3 | B3: В колонке «Продано» указывайте, сколько единиц уже продано.
A4: 4 | B4: «Остаток», «Выручка», «Себестоимость проданного» и «Прибыль» считаются автоматически.
A5: 5 | B5: Вкладка «Сводка» показывает общие показатели по складу.
A6: 6 | B6: Файл можно загрузить в Google Таблицы и работать с ним с телефона и ноутбука.
