Workbook

Sheet Запчасти
A1: Артикул | B1: Наименование | C1: Производитель | D1: Подходит к авто | E1: Категория | F1: Дата поступления | G1: Закупочная цена | H1: Цена продажи | I1: Поступило | J1: Продано | K1: Остаток | L1: Всего на сумму | M1: Выручка | N1: Себестоимость проданного | O1: Прибыль | P1: Комментарий | AI1: ID
B2: шланг Тормозной длинный | D2: УАЗ | E2: Тормоза | H2: 3000 | I2: 22 | J2: 1 | K2: =I2-J2 -> 21 | L2: =K2*H2 -> 63000 | M2: =IF(A2="","",H2*J2) | N2: =IF(A2="","",G2*J2) | O2: =IF(A2="","",M2-N2) | AI2: 1
A3: Р4-3706 020 | B3: Бегунок трамблёра | D3: ГАЗ | E3: Двигатель | H3: 1000 | I3: 6 | K3: =I3-J3 -> 6 | L3: =K3*H3 -> 6000 | M3: =IF(A3="","",H3*J3) -> 0 | N3: =IF(A3="","",G3*J3) -> 0 | O3: =IF(A3="","",M3-N3) -> 0 | AI3: 2
B4: Блок управления отопителем | D4: Газель | E4: Другое | H4: 5000 | I4: 1 | K4: =I4-J4 -> 1 | L4: =K4*H4 -> 5000 | M4: =IF(A4="","",H4*J4) | N4: =IF(A4="","",G4*J4) | O4: =IF(A4="","",M4-N4) | AI4: 3
A5: 521701080 | B5: Блок шестерен заднего хода | D5: ГАЗ | E5: Подвеска | H5: 17000 | I5: 7 | K5: =I5-J5 -> 7 | L5: =K5*H5 -> 119000 | M5: =IF(A5="","",H5*J5) -> 0 | N5: =IF(A5="","",G5*J5) -> 0 | O5: =IF(A5="","",M5-N5) -> 0 | AI5: 4
B6: Блок шестерен КПП | D6: ГАЗ | E6: Подвеска | H6: 50000 | I6: 7 | K6: =I6-J6 -> 7 | L6: =K6*H6 -> 350000 | M6: =IF(A6="","",H6*J6) | N6: =IF(A6="","",G6*J6) | O6: =IF(A6="","",M6-N6) | AI6: 5
A7: 53121701306 | B7: Блок шестерен КПП | D7: ГАЗ 53 | E7: Подвеска | H7: 90000 | I7: 3 | K7: =I7-J7 -> 3 | L7: =K7*H7 -> 270000 | M7: =IF(A7="","",H7*J7) -> 0 | N7: =IF(A7="","",G7*J7) -> 0 | O7: =IF(A7="","",M7-N7) -> 0 | AI7: 6
B8: Болт генератора | D8: УАЗ/ ГАЗ | E8: Другое | H8: 300 | I8: 25 | K8: =I8-J8 -> 25 | L8: =K8*H8 -> 7500 | M8: =IF(A8="","",H8*J8) | N8: =IF(A8="","",G8*J8) | O8: =IF(A8="","",M8-N8) | AI8: 7
B9: Болт главной пары | D9: УАЗ | E9: Подвеска | H9: 200 | I9: 105 | K9: =I9-J9 -> 105 | L9: =K9*H9 -> 21000 | M9: =IF(A9="","",H9*J9) | N9: =IF(A9="","",G9*J9) | O9: =IF(A9="","",M9-N9) | AI9: 8
B10: Болт кардана с гайкой, шайбой | D10: Уаз | E10: Подвеска | H10: 300 | I10: 42 | K10: =I10-J10 -> 42 | L10: =K10*H10 -> 12600 | M10: =IF(A10="","",H10*J10) | N10: =IF(A10="","",G10*J10) | O10: =IF(A10="","",M10-N10) | AI10: 9
A11: M10x1x35 | B11: Болт картера моста | D11: УАЗ | E11: Другое | H11: 300 | I11: 180 | K11: =I11-J11 -> 180 | L11: =K11*H11 -> 54000 | M11: =IF(A11="","",H11*J11) -> 0 | N11: =IF(A11="","",G11*J11) -> 0 | O11: =IF(A11="","",M11-N11) -> 0 | AI11: 10
A12: M10x25 | B12: Болт крепления полуоси | D12: УАЗ | E12: Другое | H12: 300 | I12: 25 | K12: =I12-J12 -> 25 | L12: =K12*H12 -> 7500 | M12: =IF(A12="","",H12*J12) -> 0 | N12: =IF(A12="","",G12*J12) -> 0 | O12: =IF(A12="","",M12-N12) -> 0 | AI12: 11
A13: 66-1007075-02 | B13: Болт с гайкой для регулировки карамысла | D13: УАЗ/ ГАЗ | E13: Двигатель | H13: 500 | I13: 32 | K13: =I13-J13 -> 32 | L13: =K13*H13 -> 16000 | M13: =IF(A13="","",H13*J13) -> 0 | N13: =IF(A13="","",G13*J13) -> 0 | O13: =IF(A13="","",M13-N13) -> 0 | AI13: 12
A14: 3151350106810 | B14: Болт эксцентриковый для регулировки передних колодок | D14: УАЗ | E14: Тормоза | H14: 1500 | I14: 19 | K14: =I14-J14 -> 19 | L14: =K14*H14 -> 28500 | M14: =IF(A14="","",H14*J14) -> 0 | N14: =IF(A14="","",G14*J14) -> 0 | O14: =IF(A14="","",M14-N14) -> 0 | AI14: 13
B15: Болт m10x1.25x33.5 | D15: УАЗ/ ГАЗ | E15: Другое | H15: 300 | I15: 18 | K15: =I15-J15 -> 18 | L15: =K15*H15 -> 5400 | M15: =IF(A15="","",H15*J15) | N15: =IF(A15="","",G15*J15) | O15: =IF(A15="","",M15-N15) | AI15: 14
A16: 452001701105 | B16: Вал вторичный | D16: УАЗ | E16: Подвеска | H16: 15000 | I16: 2 | K16: =I16-J16 -> 2 | L16: =K16*H16 -> 30000 | M16: =IF(A16="","",H16*J16) -> 0 | N16: =IF(A16="","",G16*J16) -> 0 | O16: =IF(A16="","",M16-N16) -> 0 | AI16: 15
A17: 3741170215095 | B17: Вал муфты механизма переключения передач | D17: УАЗ | E17: Подвеска | H17: 3000 | I17: 4 | K17: =I17-J17 -> 4 | L17: =K17*H17 -> 12000 | M17: =IF(A17="","",H17*J17) -> 0 | N17: =IF(A17="","",G17*J17) -> 0 | O17: =IF(A17="","",M17-N17) -> 0 | AI17: 16
A18: 31621802054 | B18: Вал привода заднего моста РК | D18: УАЗ | E18: Подвеска | H18: 30000 | I18: 3 | K18: =I18-J18 -> 3 | L18: =K18*H18 -> 90000 | M18: =IF(A18="","",H18*J18) -> 0 | N18: =IF(A18="","",G18*J18) -> 0 | O18: =IF(A18="","",M18-N18) -> 0 | AI18: 17
A19: 316200180211000 | B19: Вал привода переднего моста выходной вал раздатки | D19: УАЗ | E19: Подвеска | H19: 25000 | I19: 2 | K19: =I19-J19 -> 2 | L19: =K19*H19 -> 50000 | M19: =IF(A19="","",H19*J19) -> 0 | N19: =IF(A19="","",G19*J19) -> 0 | O19: =IF(A19="","",M19-N19) -> 0 | AI19: 18
A20: 374100170125000 | B20: Вал промежуточный | D20: УАЗ | E20: Подвеска | H20: 22000 | I20: 1 | K20: =I20-J20 -> 1 | L20: =K20*H20 -> 22000 | M20: =IF(A20="","",H20*J20) -> 0 | N20: =IF(A20="","",G20*J20) -> 0 | O20: =IF(A20="","",M20-N20) -> 0 | AI20: 19
A21: 21А1005125 | B21: Венец маховика | D21: УАЗ/ ГАЗ | E21: Двигатель | H21: 10000 | I21: 7 | K21: =I21-J21 -> 7 | L21: =K21*H21 -> 70000 | M21: =IF(A21="","",H21*J21) -> 0 | N21: =IF(A21="","",G21*J21) -> 0 | O21: =IF(A21="","",M21-N21) -> 0 | AI21: 20
A22: 241308010 | B22: Вентилятор охлаждения | D22: УАЗ/ ГАЗ | E22: Двигатель | H22: 3000 | I22: 1 | K22: =I22-J22 -> 1 | L22: =K22*H22 -> 3000 | M22: =IF(A22="","",H22*J22) -> 0 | N22: =IF(A22="","",G22*J22) -> 0 | O22: =IF(A22="","",M22-N22) -> 0 | AI22: 21
A23: 33021702024 | B23: Вилка КПП | D23: Газель | E23: Подвеска | H23: 8000 | I23: 3 | K23: =I23-J23 -> 3 | L23: =K23*H23 -> 24000 | M23: =IF(A23="","",H23*J23) -> 0 | N23: =IF(A23="","",G23*J23) -> 0 | O23: =IF(A23="","",M23-N23) -> 0 | AI23: 22
A24: 45200170202402 | B24: Вилка КПП 1й-2й передачи с/о | D24: УАЗ | E24: Подвеска | H24: 8000 | I24: 1 | K24: =I24-J24 -> 1 | L24: =K24*H24 -> 8000 | M24: =IF(A24="","",H24*J24) -> 0 | N24: =IF(A24="","",G24*J24) -> 0 | O24: =IF(A24="","",M24-N24) -> 0 | AI24: 23
A25: СТ2303708020 | B25: Вилка стартера | D25: УАЗ/ ГАЗ | E25: Двигатель | H25: 1500 | I25: 4 | K25: =I25-J25 -> 4 | L25: =K25*H25 -> 6000 | M25: =IF(A25="","",H25*J25) -> 0 | N25: =IF(A25="","",G25*J25) -> 0 | O25: =IF(A25="","",M25-N25) -> 0 | AI25: 24
B26: Вилка ШРУСа | D26: УАЗ | E26: Подвеска | H26: 12000 | I26: 3 | K26: =I26-J26 -> 3 | L26: =K26*H26 -> 36000 | M26: =IF(A26="","",H26*J26) | N26: =IF(A26="","",G26*J26) | O26: =IF(A26="","",M26-N26) | AI26: 25
A27: 316000230402312 | B27: Вкладыш шкворня | D27: УАЗ | E27: Подвеска | H27: 1000 | I27: 11 | K27: =I27-J27 -> 11 | L27: =K27*H27 -> 11000 | M27: =IF(A27="","",H27*J27) -> 0 | N27: =IF(A27="","",G27*J27) -> 0 | O27: =IF(A27="","",M27-N27) -> 0 | AI27: 26
A28: 24100010231 | B28: Вкладыши коренные 0.50 | D28: УАЗ/ГАЗ | E28: Двигатель | H28: 10000 | I28: 2 | K28: =I28-J28 -> 2 | L28: =K28*H28 -> 20000 | M28: =IF(A28="","",H28*J28) -> 0 | N28: =IF(A28="","",G28*J28) -> 0 | O28: =IF(A28="","",M28-N28) -> 0 | AI28: 27
A29: 24100010202 | B29: Вкладыши шатунные 0.25 | D29: УАЗ/ГАЗ | E29: Двигатель | H29: 10000 | I29: 3 | K29: =I29-J29 -> 3 | L29: =K29*H29 -> 30000 | M29: =IF(A29="","",H29*J29) -> 0 | N29: =IF(A29="","",G29*J29) -> 0 | O29: =IF(A29="","",M29-N29) -> 0 | AI29: 28
A30: 241000104 | B30: Вкладыши шатунные 0.75 | D30: УАЗ/ГАЗ | E30: Двигатель | H30: 10000 | I30: 1 | K30: =I30-J30 -> 1 | L30: =K30*H30 -> 10000 | M30: =IF(A30="","",H30*J30) -> 0 | N30: =IF(A30="","",G30*J30) -> 0 | O30: =IF(A30="","",M30-N30) -> 0 | AI30: 29
A31: 4691701105 | B31: Вторичный вал | D31: УАЗ | E31: Подвеска | H31: 15000 | I31: 3 | K31: =I31-J31 -> 3 | L31: =K31*H31 -> 45000 | M31: =IF(A31="","",H31*J31) -> 0 | N31: =IF(A31="","",G31*J31) -> 0 | O31: =IF(A31="","",M31-N31) -> 0 | AI31: 30
A32: 53121701101 | B32: Вторичный вал КПП | D32: ГАЗ | E32: Подвеска | H32: 25000 | I32: 6 | K32: =I32-J32 -> 6 | L32: =K32*H32 -> 150000 | M32: =IF(A32="","",H32*J32) -> 0 | N32: =IF(A32="","",G32*J32) -> 0 | O32: =IF(A32="","",M32-N32) -> 0 | AI32: 31
B33: Втулка шатуна | D33: УАЗ/ ГАЗ | E33: Двигатель | H33: 1500 | I33: 11 | K33: =I33-J33 -> 11 | L33: =K33*H33 -> 16500 | M33: =IF(A33="","",H33*J33) | N33: =IF(A33="","",G33*J33) | O33: =IF(A33="","",M33-N33) | AI33: 32
B34: Выключатель массы | D34: ГАЗ 53 | E34: Электрика | H34: 3000 | I34: 3 | K34: =I34-J34 -> 3 | L34: =K34*H34 -> 9000 | M34: =IF(A34="","",H34*J34) | N34: =IF(A34="","",G34*J34) | O34: =IF(A34="","",M34-N34) | AI34: 33
A35: 211009070 | B35: Высоковольтные провода (комплект) | D35: УАЗ/ ГАЗ | E35: Двигатель | H35: 4000 | I35: 7 | K35: =I35-J35 -> 7 | L35: =K35*H35 -> 28000 | M35: =IF(A35="","",H35*J35) -> 0 | N35: =IF(A35="","",G35*J35) -> 0 | O35: =IF(A35="","",M35-N35) -> 0 | AI35: 34
B36: Высоковольтный провод (длинный) | E36: Двигатель | H36: 1000 | I36: 16 | K36: =I36-J36 -> 16 | L36: =K36*H36 -> 16000 | M36: =IF(A36="","",H36*J36) | N36: =IF(A36="","",G36*J36) | O36: =IF(A36="","",M36-N36) | AI36: 35
B37: Высоковольтный провод (короткий) | E37: Двигатель | H37: 500 | I37: 15 | K37: =I37-J37 -> 15 | L37: =K37*H37 -> 7500 | M37: =IF(A37="","",H37*J37) | N37: =IF(A37="","",G37*J37) | O37: =IF(A37="","",M37-N37) | AI37: 36
B38: Гайка колёсная ГАЗ 53 | D38: ГАЗ 53 | E38: Подвеска | H38: 1000 | I38: 6 | K38: =I38-J38 -> 6 | L38: =K38*H38 -> 6000 | M38: =IF(A38="","",H38*J38) | N38: =IF(A38="","",G38*J38) | O38: =IF(A38="","",M38-N38) | AI38: 37
A39: 531601178 | B39: Гайка регулирования лапки сцепления | D39: УАЗ/ ГАЗ | E39: Подвеска | H39: 500 | I39: 105 | K39: =I39-J39 -> 105 | L39: =K39*H39 -> 52500 | M39: =IF(A39="","",H39*J39) -> 0 | N39: =IF(A39="","",G39*J39) -> 0 | O39: =IF(A39="","",M39-N39) -> 0 | AI39: 38
A40: M12x1.25x10 | B40: Гайка стойки стабилизатора | D40: УАЗ | E40: Подвеска | H40: 200 | I40: 214 | K40: =I40-J40 -> 214 | L40: =K40*H40 -> 42800 | M40: =IF(A40="","",H40*J40) -> 0 | N40: =IF(A40="","",G40*J40) -> 0 | O40: =IF(A40="","",M40-N40) -> 0 | AI40: 39
A41: 664502218 | B41: Гайка фланца раздаточной коробки | D41: ГАЗ | E41: Подвеска | H41: 1000 | I41: 10 | K41: =I41-J41 -> 10 | L41: =K41*H41 -> 10000 | M41: =IF(A41="","",H41*J41) -> 0 | N41: =IF(A41="","",G41*J41) -> 0 | O41: =IF(A41="","",M41-N41) -> 0 | AI41: 40
B42: Гитара | D42: ГАЗ | E42: Электрика | H42: 20000 | I42: 1 | K42: =I42-J42 -> 1 | L42: =K42*H42 -> 20000 | M42: =IF(A42="","",H42*J42) | N42: =IF(A42="","",G42*J42) | O42: =IF(A42="","",M42-N42) | AI42: 41
A43: 453471125 | B43: ГУР | D43: УАЗ/ГАЗ | E43: Двигатель | H43: 100000 | I43: 1 | K43: =I43-J43 -> 1 | L43: =K43*H43 -> 100000 | M43: =IF(A43="","",H43*J43) -> 0 | N43: =IF(A43="","",G43*J43) -> 0 | O43: =IF(A43="","",M43-N43) -> 0 | AI43: 42
A44: 4933843 | B44: Датчик электронного спидометра | D44: УАЗ/ ВАЗ | E44: Электрика | H44: 2500 | I44: 2 | K44: =I44-J44 -> 2 | L44: =K44*H44 -> 5000 | M44: =IF(A44="","",H44*J44) -> 0 | N44: =IF(A44="","",G44*J44) -> 0 | O44: =IF(A44="","",M44-N44) -> 0 | AI44: 43
A45: 31633538030 | B45: Диск АБС | D45: УАЗ | E45: Тормоза | H45: 10000 | I45: 3 | K45: =I45-J45 -> 3 | L45: =K45*H45 -> 30000 | M45: =IF(A45="","",H45*J45) -> 0 | N45: =IF(A45="","",G45*J45) -> 0 | O45: =IF(A45="","",M45-N45) -> 0 | AI45: 44
A46: 316300350108805 | B46: Дисковые колодки тормозные | D46: УАЗ Буханка | E46: Тормоза | H46: 8000 | I46: 9 | K46: =I46-J46 -> 9 | L46: =K46*H46 -> 72000 | M46: =IF(A46="","",H46*J46) -> 0 | N46: =IF(A46="","",G46*J46) -> 0 | O46: =IF(A46="","",M46-N46) -> 0 | AI46: 45
B47: Дифференциал с главной парой | D47: УАЗ | E47: Подвеска | H47: 150000 | I47: 2 | K47: =I47-J47 -> 2 | L47: =K47*H47 -> 300000 | M47: =IF(A47="","",H47*J47) | N47: =IF(A47="","",G47*J47) | O47: =IF(A47="","",M47-N47) | AI47: 46
A48: 3163008110920 | B48: Дополнительный насос отопителя | D48: УАЗ | E48: Двигатель | H48: 12000 | I48: 1 | K48: =I48-J48 -> 1 | L48: =K48*H48 -> 12000 | M48: =IF(A48="","",H48*J48) -> 0 | N48: =IF(A48="","",G48*J48) -> 0 | O48: =IF(A48="","",M48-N48) -> 0 | AI48: 47
B49: Жидкость тормозная | D49: ВСЕ | E49: Расходники | H49: 1000 | I49: 2 | K49: =I49-J49 -> 2 | L49: =K49*H49 -> 2000 | M49: =IF(A49="","",H49*J49) | N49: =IF(A49="","",G49*J49) | O49: =IF(A49="","",M49-N49) | AI49: 48
A50: 220600350209110 | B50: Задние тормозные колодки | D50: УАЗ Буханка | E50: Тормоза | H50: 5000 | I50: 49 | K50: =I50-J50 -> 49 | L50: =K50*H50 -> 245000 | M50: =IF(A50="","",H50*J50) -> 0 | N50: =IF(A50="","",G50*J50) -> 0 | O50: =IF(A50="","",M50-N50) -> 0 | AI50: 49
A51: 4693501070 | B51: Задний тормозной барабан | C51: Уаз | D51: УАЗ Буханка | E51: Тормоза | H51: 20000 | I51: 13 | K51: =I51-J51 -> 13 | L51: =K51*H51 -> 260000 | M51: =IF(A51="","",H51*J51) -> 0 | N51: =IF(A51="","",G51*J51) -> 0 | O51: =IF(A51="","",M51-N51) -> 0 | AI51: 50
A52: 31513502040 | B52: Задний тормозной цилиндр 25мм | D52: УАЗ | E52: Тормоза | H52: 8000 | I52: 15 | K52: =I52-J52 -> 15 | L52: =K52*H52 -> 120000 | M52: =IF(A52="","",H52*J52) -> 0 | N52: =IF(A52="","",G52*J52) -> 0 | O52: =IF(A52="","",M52-N52) -> 0 | AI52: 51
A53: 4693502040 | B53: Задний тормозной цилиндр 32мм | D53: УАЗ | E53: Тормоза | H53: 8000 | I53: 9 | K53: =I53-J53 -> 9 | L53: =K53*H53 -> 72000 | M53: =IF(A53="","",H53*J53) -> 0 | N53: =IF(A53="","",G53*J53) -> 0 | O53: =IF(A53="","",M53-N53) -> 0 | AI53: 52
A54: 316300811001007 | B54: Задняя печка патриот | D54: Уаз | E54: Электрика | H54: 65000 | I54: 1 | K54: =I54-J54 -> 1 | L54: =K54*H54 -> 65000 | M54: =IF(A54="","",H54*J54) -> 0 | N54: =IF(A54="","",G54*J54) -> 0 | O54: =IF(A54="","",M54-N54) -> 0 | AI54: 53
A55: К126Г | B55: Карбюратор | D55: УАЗ | E55: Двигатель | H55: 60000 | I55: 1 | K55: =I55-J55 -> 1 | L55: =K55*H55 -> 60000 | M55: =IF(A55="","",H55*J55) -> 0 | N55: =IF(A55="","",G55*J55) -> 0 | O55: =IF(A55="","",M55-N55) -> 0 | AI55: 54
A56: 3302 | B56: Карбюратор Газель | D56: Газель | E56: Двигатель | H56: 70000 | I56: 1 | K56: =I56-J56 -> 1 | L56: =K56*H56 -> 70000 | M56: =IF(A56="","",H56*J56) -> 0 | N56: =IF(A56="","",G56*J56) -> 0 | O56: =IF(A56="","",M56-N56) -> 0 | AI56: 55
A57: 296515 | B57: Катафот задний | D57: УАЗ | E57: Кузов | H57: 2000 | I57: 8 | K57: =I57-J57 -> 8 | L57: =K57*H57 -> 16000 | M57: =IF(A57="","",H57*J57) -> 0 | N57: =IF(A57="","",G57*J57) -> 0 | O57: =IF(A57="","",M57-N57) -> 0 | AI57: 56
A58: 31513510178 | B58: Клапан вакуумный обратный | D58: УАЗ/ ГАЗ | E58: Тормоза | H58: 2000 | I58: 6 | K58: =I58-J58 -> 6 | L58: =K58*H58 -> 12000 | M58: =IF(A58="","",H58*J58) -> 0 | N58: =IF(A58="","",G58*J58) -> 0 | O58: =IF(A58="","",M58-N58) -> 0 | AI58: 57
A59: 4021007010 | B59: Клапан ГБЦ | D59: УАЗ | E59: Двигатель | H59: 3000 | I59: 2 | K59: =I59-J59 -> 2 | L59: =K59*H59 -> 6000 | M59: =IF(A59="","",H59*J59) -> 0 | N59: =IF(A59="","",G59*J59) -> 0 | O59: =IF(A59="","",M59-N59) -> 0 | AI59: 58
B60: Клипса-пистон для обшивки | D60: УАЗ | E60: Кузов | H60: 50 | I60: 61 | K60: =I60-J60 -> 61 | L60: =K60*H60 -> 3050 | M60: =IF(A60="","",H60*J60) | N60: =IF(A60="","",G60*J60) | O60: =IF(A60="","",M60-N60) | AI60: 59
A61: 66-1601015-11 | B61: Колокол сцепления | D61: ГАЗ 53 | E61: Подвеска | H61: 120000 | I61: 1 | K61: =I61-J61 -> 1 | L61: =K61*H61 -> 120000 | M61: =IF(A61="","",H61*J61) -> 0 | N61: =IF(A61="","",G61*J61) -> 0 | O61: =IF(A61="","",M61-N61) -> 0 | AI61: 60
A62: 0469-00-1602558-00 | B62: Колпачок защитный ГЦС | D62: УАЗ | E62: Подвеска | H62: 500 | I62: 10 | K62: =I62-J62 -> 10 | L62: =K62*H62 -> 5000 | M62: =IF(A62="","",H62*J62) -> 0 | N62: =IF(A62="","",G62*J62) -> 0 | O62: =IF(A62="","",M62-N62) -> 0 | AI62: 61
A63: 24-10-1602528 | B63: Колпачок защитный ГЦС | D63: ГАЗ | E63: Подвеска | H63: 500 | I63: 7 | K63: =I63-J63 -> 7 | L63: =K63*H63 -> 3500 | M63: =IF(A63="","",H63*J63) -> 0 | N63: =IF(A63="","",G63*J63) -> 0 | O63: =IF(A63="","",M63-N63) -> 0 | AI63: 62
A64: 5311702126 | B64: Колпачок защитный на крышку кпп | D64: ГАЗ | E64: Подвеска | H64: 1500 | I64: 9 | K64: =I64-J64 -> 9 | L64: =K64*H64 -> 13500 | M64: =IF(A64="","",H64*J64) -> 0 | N64: =IF(A64="","",G64*J64) -> 0 | O64: =IF(A64="","",M64-N64) -> 0 | AI64: 63
A65: 4691701164 | B65: Кольцо синхронизатора н/о | D65: УАЗ | E65: Подвеска | H65: 6000 | I65: 28 | K65: =I65-J65 -> 28 | L65: =K65*H65 -> 168000 | M65: =IF(A65="","",H65*J65) -> 0 | N65: =IF(A65="","",G65*J65) -> 0 | O65: =IF(A65="","",M65-N65) -> 0 | AI65: 64
B66: Кольцо синхронизатора с/о | D66: УАЗ | E66: Подвеска | H66: 6000 | I66: 14 | K66: =I66-J66 -> 14 | L66: =K66*H66 -> 84000 | M66: =IF(A66="","",H66*J66) | N66: =IF(A66="","",G66*J66) | O66: =IF(A66="","",M66-N66) | AI66: 65
A67: 6900310302400 | B67: Кольцо упорное ступицы колеса | D67: УАЗ | E67: Подвеска | H67: 1000 | I67: 5 | K67: =I67-J67 -> 5 | L67: =K67*H67 -> 5000 | M67: =IF(A67="","",H67*J67) -> 0 | N67: =IF(A67="","",G67*J67) -> 0 | O67: =IF(A67="","",M67-N67) -> 0 | AI67: 66
A68: 531008000 | B68: Комплект прокладок впускного коллектора | D68: ГАЗ 53 | E68: Двигатель | H68: 4000 | I68: 6 | K68: =I68-J68 -> 6 | L68: =K68*H68 -> 24000 | M68: =IF(A68="","",H68*J68) -> 0 | N68: =IF(A68="","",G68*J68) -> 0 | O68: =IF(A68="","",M68-N68) -> 0 | AI68: 67
B69: Комплект прокладок КПП 452 | D69: УАЗ | E69: Подвеска | H69: 3000 | I69: 8 | K69: =I69-J69 -> 8 | L69: =K69*H69 -> 24000 | M69: =IF(A69="","",H69*J69) | N69: =IF(A69="","",G69*J69) | O69: =IF(A69="","",M69-N69) | AI69: 68
A70: 211009070 | B70: Комплект прокладок масляного поддона ЗМЗ 417 | D70: УАЗ/ ГАЗ | E70: Двигатель | H70: 2000 | I70: 3 | K70: =I70-J70 -> 3 | L70: =K70*H70 -> 6000 | M70: =IF(A70="","",H70*J70) -> 0 | N70: =IF(A70="","",G70*J70) -> 0 | O70: =IF(A70="","",M70-N70) -> 0 | AI70: 69
B71: Комплект прокладок моста | D71: УАЗ | E71: Подвеска | H71: 3000 | I71: 3 | K71: =I71-J71 -> 3 | L71: =K71*H71 -> 9000 | M71: =IF(A71="","",H71*J71) | N71: =IF(A71="","",G71*J71) | O71: =IF(A71="","",M71-N71) | AI71: 70
A72: 4171000150 | B72: Комплект прокладок на ЗМЗ 417 | D72: УАЗ/ ГАЗ | E72: Двигатель | H72: 15000 | I72: 1 | K72: =I72-J72 -> 1 | L72: =K72*H72 -> 15000 | M72: =IF(A72="","",H72*J72) -> 0 | N72: =IF(A72="","",G72*J72) -> 0 | O72: =IF(A72="","",M72-N72) -> 0 | AI72: 71
B73: Комплект прокладок на РК | D73: УАЗ | E73: Подвеска | H73: 3000 | I73: 20 | K73: =I73-J73 -> 20 | L73: =K73*H73 -> 60000 | M73: =IF(A73="","",H73*J73) | N73: =IF(A73="","",G73*J73) | O73: =IF(A73="","",M73-N73) | AI73: 72
A74: 4171000150 | B74: Комплект прокладок УМЗ 4178 | D74: УАЗ/ ГАЗ | E74: Двигатель | H74: 1000 | I74: 6 | K74: =I74-J74 -> 6 | L74: =K74*H74 -> 6000 | M74: =IF(A74="","",H74*J74) -> 0 | N74: =IF(A74="","",G74*J74) -> 0 | O74: =IF(A74="","",M74-N74) -> 0 | AI74: 73
B75: Комплект уплотнительных колец | E75: Другое | H75: 2000 | I75: 1 | K75: =I75-J75 -> 1 | L75: =K75*H75 -> 2000 | M75: =IF(A75="","",H75*J75) | N75: =IF(A75="","",G75*J75) | O75: =IF(A75="","",M75-N75) | AI75: 74
B76: Комплект эксцентриковый регулировочный задних тормозных колодок | D76: УАЗ | E76: Тормоза | H76: 3000 | I76: 11 | K76: =I76-J76 -> 11 | L76: =K76*H76 -> 33000 | M76: =IF(A76="","",H76*J76) | N76: =IF(A76="","",G76*J76) | O76: =IF(A76="","",M76-N76) | AI76: 75
B77: Корпус дифференциала с сателлитами | D77: УАЗ | E77: Подвеска | H77: 30000 | I77: 1 | K77: =I77-J77 -> 1 | L77: =K77*H77 -> 30000 | M77: =IF(A77="","",H77*J77) | N77: =IF(A77="","",G77*J77) | O77: =IF(A77="","",M77-N77) | AI77: 76
A78: 452170101522 | B78: Корпус КПП старого образца | D78: УАЗ | E78: Подвеска | H78: 65000 | I78: 2 | K78: =I78-J78 -> 2 | L78: =K78*H78 -> 130000 | M78: =IF(A78="","",H78*J78) -> 0 | N78: =IF(A78="","",G78*J78) -> 0 | O78: =IF(A78="","",M78-N78) -> 0 | AI78: 77
B79: Корпус поворотного кулака левый | D79: УАЗ | E79: Подвеска | H79: 60000 | I79: 1 | K79: =I79-J79 -> 1 | L79: =K79*H79 -> 60000 | M79: =IF(A79="","",H79*J79) | N79: =IF(A79="","",G79*J79) | O79: =IF(A79="","",M79-N79) | AI79: 78
B80: Корпус поворотного кулака правый | D80: УАЗ | E80: Подвеска | H80: 60000 | I80: 1 | K80: =I80-J80 -> 1 | L80: =K80*H80 -> 60000 | M80: =IF(A80="","",H80*J80) | N80: =IF(A80="","",G80*J80) | O80: =IF(A80="","",M80-N80) | AI80: 79
A81: 4521802014 | B81: Корпус РК | D81: УАЗ | E81: Подвеска | H81: 120000 | I81: 2 | K81: =I81-J81 -> 2 | L81: =K81*H81 -> 240000 | M81: =IF(A81="","",H81*J81) -> 0 | N81: =IF(A81="","",G81*J81) -> 0 | O81: =IF(A81="","",M81-N81) -> 0 | AI81: 80
A82: 2705642533401 | B82: Корпус фиксатора двери боковой | D82: Газель | E82: Кузов | H82: 1500 | I82: 1 | K82: =I82-J82 -> 1 | L82: =K82*H82 -> 1500 | M82: =IF(A82="","",H82*J82) -> 0 | N82: =IF(A82="","",G82*J82) -> 0 | O82: =IF(A82="","",M82-N82) -> 0 | AI82: 81
A83: 4521700010 | B83: КПП 4-ст старого образца | D83: Уаз | E83: Подвеска | H83: 300000 | I83: 1 | K83: =I83-J83 -> 1 | L83: =K83*H83 -> 300000 | M83: =IF(A83="","",H83*J83) -> 0 | N83: =IF(A83="","",G83*J83) -> 0 | O83: =IF(A83="","",M83-N83) -> 0 | AI83: 82
A84: 315120291551000 | B84: Кранштейн амортизатора заднего моста | D84: УАЗ | E84: Подвеска | H84: 2000 | I84: 13 | K84: =I84-J84 -> 13 | L84: =K84*H84 -> 26000 | M84: =IF(A84="","",H84*J84) -> 0 | N84: =IF(A84="","",G84*J84) -> 0 | O84: =IF(A84="","",M84-N84) -> 0 | AI84: 83
A85: 45100170310331 | B85: Кранштейн промежуточных рычагов КПП | D85: УАЗ | E85: Подвеска | H85: 8000 | I85: 1 | K85: =I85-J85 -> 1 | L85: =K85*H85 -> 8000 | M85: =IF(A85="","",H85*J85) -> 0 | N85: =IF(A85="","",G85*J85) -> 0 | O85: =IF(A85="","",M85-N85) -> 0 | AI85: 84
A86: 21052202025 | B86: Крестовина Жигули | D86: ВАЗ | E86: Подвеска | H86: 3000 | I86: 16 | K86: =I86-J86 -> 16 | L86: =K86*H86 -> 48000 | M86: =IF(A86="","",H86*J86) -> 0 | N86: =IF(A86="","",G86*J86) -> 0 | O86: =IF(A86="","",M86-N86) -> 0 | AI86: 85
A87: 3102220102522 | B87: Крестовина карданного вала | D87: УАЗ/ГАЗ | E87: Подвеска | H87: 10000 | I87: 28 | K87: =I87-J87 -> 28 | L87: =K87*H87 -> 280000 | M87: =IF(A87="","",H87*J87) -> 0 | N87: =IF(A87="","",G87*J87) -> 0 | O87: =IF(A87="","",M87-N87) -> 0 | AI87: 86
A88: 21212202025 | B88: Крестовина нива | D88: ВАЗ | E88: Подвеска | H88: 4000 | I88: 1 | K88: =I88-J88 -> 1 | L88: =K88*H88 -> 4000 | M88: =IF(A88="","",H88*J88) -> 0 | N88: =IF(A88="","",G88*J88) -> 0 | O88: =IF(A88="","",M88-N88) -> 0 | AI88: 87
A89: 31602905550 | B89: Кронштейн нижний переднего амортизатора | D89: УАЗ | E89: Подвеска | H89: 2000 | I89: 2 | K89: =I89-J89 -> 2 | L89: =K89*H89 -> 4000 | M89: =IF(A89="","",H89*J89) -> 0 | N89: =IF(A89="","",G89*J89) -> 0 | O89: =IF(A89="","",M89-N89) -> 0 | AI89: 88
A90: 45150290244592 | B90: Кронштейн рессоры | D90: УАЗ | E90: Подвеска | H90: 15000 | I90: 4 | K90: =I90-J90 -> 4 | L90: =K90*H90 -> 60000 | M90: =IF(A90="","",H90*J90) -> 0 | N90: =IF(A90="","",G90*J90) -> 0 | O90: =IF(A90="","",M90-N90) -> 0 | AI90: 89
B91: Крыльчатка помпы | D91: ГАЗ 53 | E91: Двигатель | H91: 8000 | I91: 1 | K91: =I91-J91 -> 1 | L91: =K91*H91 -> 8000 | M91: =IF(A91="","",H91*J91) | N91: =IF(A91="","",G91*J91) | O91: =IF(A91="","",M91-N91) | AI91: 90
A92: 451170201510 | B92: Крышка КПП | D92: УАЗ | E92: Подвеска | H92: 25000 | I92: 4 | K92: =I92-J92 -> 4 | L92: =K92*H92 -> 100000 | M92: =IF(A92="","",H92*J92) -> 0 | N92: =IF(A92="","",G92*J92) -> 0 | O92: =IF(A92="","",M92-N92) -> 0 | AI92: 91
B93: Крышка КПП Газ 3307 | D93: ГАЗ | E93: Подвеска | H93: 35000 | I93: 1 | K93: =I93-J93 -> 1 | L93: =K93*H93 -> 35000 | M93: =IF(A93="","",H93*J93) | N93: =IF(A93="","",G93*J93) | O93: =IF(A93="","",M93-N93) | AI93: 92
A94: 53А170201002 | B94: Крышка КПП на газ 3307 в сборе | D94: ГАЗ | E94: Подвеска | H94: 65000 | I94: 3 | K94: =I94-J94 -> 3 | L94: =K94*H94 -> 195000 | M94: =IF(A94="","",H94*J94) -> 0 | N94: =IF(A94="","",G94*J94) -> 0 | O94: =IF(A94="","",M94-N94) -> 0 | AI94: 93
A95: 469170201530 | B95: Крышка КПП старого образца | D95: УАЗ | E95: Подвеска | H95: 25000 | I95: 1 | K95: =I95-J95 -> 1 | L95: =K95*H95 -> 25000 | M95: =IF(A95="","",H95*J95) -> 0 | N95: =IF(A95="","",G95*J95) -> 0 | O95: =IF(A95="","",M95-N95) -> 0 | AI95: 94
A96: 521701020 | B96: Крышка люка вала отбора мощности или КПП | D96: ГАЗ | E96: Подвеска | H96: 3000 | I96: 8 | K96: =I96-J96 -> 8 | L96: =K96*H96 -> 24000 | M96: =IF(A96="","",H96*J96) -> 0 | N96: =IF(A96="","",G96*J96) -> 0 | O96: =IF(A96="","",M96-N96) -> 0 | AI96: 95
A97: 4691701070 | B97: Крышка переднего подшипника промежуточного вала | D97: УАЗ | E97: Подвеска | H97: 1000 | I97: 4 | K97: =I97-J97 -> 4 | L97: =K97*H97 -> 4000 | M97: =IF(A97="","",H97*J97) -> 0 | N97: =IF(A97="","",G97*J97) -> 0 | O97: =IF(A97="","",M97-N97) -> 0 | AI97: 96
A98: 4691701068 | B98: Крышка передняя подшипника промвала | D98: УАЗ | E98: Подвеска | H98: 1000 | I98: 5 | K98: =I98-J98 -> 5 | L98: =K98*H98 -> 5000 | M98: =IF(A98="","",H98*J98) -> 0 | N98: =IF(A98="","",G98*J98) -> 0 | O98: =IF(A98="","",M98-N98) -> 0 | AI98: 97
A99: 53121701200 | B99: Крышка подшипника вторичного вала | D99: ГАЗ 53 | E99: Подвеска | H99: 20000 | I99: 1 | K99: =I99-J99 -> 1 | L99: =K99*H99 -> 20000 | M99: =IF(A99="","",H99*J99) -> 0 | N99: =IF(A99="","",G99*J99) -> 0 | O99: =IF(A99="","",M99-N99) -> 0 | AI99: 98
A100: 451501701040 | B100: крышка подшипника первичного вала КПП | D100: Уаз | E100: Подвеска | H100: 10000 | I100: 13 | K100: =I100-J100 -> 13 | L100: =K100*H100 -> 130000 | M100: =IF(A100="","",H100*J100) -> 0 | N100: =IF(A100="","",G100*J100) -> 0 | O100: =IF(A100="","",M100-N100) -> 0 | AI100: 99
...

Sheet Сводка
A1: СВОДКА ПО СКЛАДУ И ПРОДАЖАМ
A2: Показатель | B2: Значение
A3: Всего позиций | B3: =COUNTIF('Запчасти'!B2:B501,"<>") -> 293
A4: Всего единиц на остатке | B4: =SUM('Запчасти'!K2:K501) -> 3017
A5: Всего товаров на сумму | B5: ='Запчасти'!L503 -> 14297150 | C5: =B5/450 -> 31771.444 | D5: Это в Долларах
A6: Выручка | B6: =SUM('Запчасти'!M2:M501) -> 0
A7: Себестоимость проданного | B7: =SUM('Запчасти'!N2:N501) -> 0
A8: Прибыль | B8: =SUM('Запчасти'!O2:O501) -> 0

Sheet Как пользоваться
A1: КРАТКАЯ ИНСТРУКЦИЯ | B1: Вносите каждую запчасть отдельной строкой на вкладке «Запчасти».
A2: 2 | B2: Заполняйте артикул, название, производителя, автомобиль, цены и количество.
A3: 3 | B3: В колонке «Продано» указывайте, сколько единиц уже продано.
A4: 4 | B4: «Остаток», «Выручка», «Себестоимость проданного» и «Прибыль» считаются автоматически.
A5: 5 | B5: Вкладка «Сводка» показывает общие показатели по складу.
A6: 6 | B6: Файл можно загрузить в Google Таблицы и работать с ним с телефона и ноутбука.

Sheet Заказы
A1: Номер заказа | B1: Дата и время | C1: Телефон покупателя | D1: Позиций | E1: Итого, ₸ | F1: Состав | G1: Состав (читаемо) | H1: Статус | I1: Предложено за заказ, ₸ | J1: Итого по прайсу, ₸ | K1: Комментарий
A2: ШКВ-0001 | B2: 2026-09-21T15:18:51+05:00 | C2: 87476108458 | D2: 1 | E2: 600 | F2: 6x2 | G2: Болт генератора, 2 шт × 300 ₸ = 600 ₸ | H2: новый
A3: ШКВ-0002 | B3: 2026-09-22T15:19:50+05:00 | C3: 87476108458 | D3: 1 | E3: 1000 | F3: 1x1 | G3: Р4-3706 020 — Бегунок трамблёра, 1 шт × 1 000 ₸ = 1 000 ₸ | H3: новый
A4: ШКВ-0003 | B4: 2026-09-23T12:52:32+05:00 | C4: +77476108458 | D4: 3 | E4: 15000 | F4: 241x1; 149x2; 1x3 | G4: Трапеция привода дворников, 1 шт × 6 000 ₸ = 6 000 ₸ 40x80x18 — Подшипник в раздатку 6208, 2 шт × 3 000 ₸ = 6 000 ₸ Р4-3706 020 — Бегунок трамблёра, 3 шт × 1 000 ₸ = 3 000 ₸ | H4: новый | J4: 15000 | K4: чек чек
A5: ШКВ-0004 | B5: 2026-09-23T16:25:38+05:00 | C5: 87476108458 | D5: 1 | E5: 990 | F5: 2x1@300 | G5: Блок управления отопителем, 1 шт × 5 000 ₸ = 5 000 ₸ (предложено: 300 ₸/шт = 300 ₸) | H5: новый | I5: 990 | J5: 5000
